{
"meta":{"test_sets":[],"test_metrics":[],"learn_metrics":[{"best_value":"Min","name":"RMSE"}],"launch_mode":"Train","parameters":"","iteration_count":1000,"learn_sets":["learn"],"name":"experiment"},
"iterations":[
{"learn":[14.62456878],"iteration":0,"passed_time":0.001295173965,"remaining_time":1.293878791},
{"learn":[14.23607334],"iteration":1,"passed_time":0.002320265018,"remaining_time":1.157812244},
{"learn":[13.87236985],"iteration":2,"passed_time":0.00341977632,"remaining_time":1.136505664},
{"learn":[13.54569272],"iteration":3,"passed_time":0.004462406537,"remaining_time":1.111139228},
{"learn":[13.21947217],"iteration":4,"passed_time":0.005469481289,"remaining_time":1.088426777},
{"learn":[12.92502597],"iteration":5,"passed_time":0.006452141672,"remaining_time":1.068904804},
{"learn":[12.60341348],"iteration":6,"passed_time":0.007484863843,"remaining_time":1.061781399},
{"learn":[12.29433259],"iteration":7,"passed_time":0.008500068294,"remaining_time":1.054008468},
{"learn":[12.00570834],"iteration":8,"passed_time":0.009478893971,"remaining_time":1.043731547},
{"learn":[11.72342767],"iteration":9,"passed_time":0.01046287777,"remaining_time":1.0358249},
{"learn":[11.48208873],"iteration":10,"passed_time":0.01149011326,"remaining_time":1.033065638},
{"learn":[11.23601165],"iteration":11,"passed_time":0.01252843853,"remaining_time":1.031508106},
{"learn":[10.98760318],"iteration":12,"passed_time":0.01359450127,"remaining_time":1.032136366},
{"learn":[10.74192206],"iteration":13,"passed_time":0.01459368911,"remaining_time":1.027812676},
{"learn":[10.50347949],"iteration":14,"passed_time":0.01557161412,"remaining_time":1.022535994},
{"learn":[10.28350774],"iteration":15,"passed_time":0.01655337614,"remaining_time":1.018032633},
{"learn":[10.07574341],"iteration":16,"passed_time":0.01753213748,"remaining_time":1.013770067},
{"learn":[9.882498151],"iteration":17,"passed_time":0.0185160715,"remaining_time":1.010154568},
{"learn":[9.727379727],"iteration":18,"passed_time":0.01901348806,"remaining_time":0.9816964097},
{"learn":[9.52303773],"iteration":19,"passed_time":0.02001955569,"remaining_time":0.9809582289},
{"learn":[9.335589327],"iteration":20,"passed_time":0.02101910119,"remaining_time":0.9798904791},
{"learn":[9.167141356],"iteration":21,"passed_time":0.02202145895,"remaining_time":0.9789539479},
{"learn":[9.026642926],"iteration":22,"passed_time":0.02301134914,"remaining_time":0.9774820916},
{"learn":[8.861065615],"iteration":23,"passed_time":0.02399714882,"remaining_time":0.9758840518},
{"learn":[8.696730583],"iteration":24,"passed_time":0.02498110352,"remaining_time":0.9742630372},
{"learn":[8.552373776],"iteration":25,"passed_time":0.02597431987,"remaining_time":0.9730379828},
{"learn":[8.415447527],"iteration":26,"passed_time":0.02709739581,"remaining_time":0.9765098565},
{"learn":[8.293344382],"iteration":27,"passed_time":0.02822300257,"remaining_time":0.9797413748},
{"learn":[8.173210434],"iteration":28,"passed_time":0.02930572066,"remaining_time":0.9812363711},
{"learn":[8.044891548],"iteration":29,"passed_time":0.03039379448,"remaining_time":0.9827326881},
{"learn":[7.922883538],"iteration":30,"passed_time":0.03144014069,"remaining_time":0.9827579461},
{"learn":[7.804807099],"iteration":31,"passed_time":0.03249121078,"remaining_time":0.9828591262},
{"learn":[7.697106341],"iteration":32,"passed_time":0.03350053796,"remaining_time":0.9816672789},
{"learn":[7.598566623],"iteration":33,"passed_time":0.03449381175,"remaining_time":0.9800300632},
{"learn":[7.513836891],"iteration":34,"passed_time":0.03519622461,"remaining_time":0.9704101928},
{"learn":[7.415878567],"iteration":35,"passed_time":0.036195934,"remaining_time":0.9692466771},
{"learn":[7.322562542],"iteration":36,"passed_time":0.03715954799,"remaining_time":0.9671525598},
{"learn":[7.235555249],"iteration":37,"passed_time":0.03813114999,"remaining_time":0.9653201655},
{"learn":[7.161150627],"iteration":38,"passed_time":0.03912615771,"remaining_time":0.9641086553},
{"learn":[7.08042975],"iteration":39,"passed_time":0.04012845267,"remaining_time":0.9630828642},
{"learn":[7.006216849],"iteration":40,"passed_time":0.04116665693,"remaining_time":0.9628981463},
{"learn":[6.933622376],"iteration":41,"passed_time":0.04217128091,"remaining_time":0.9619068359},
{"learn":[6.856503947],"iteration":42,"passed_time":0.04315057683,"remaining_time":0.9603512098},
{"learn":[6.793482695],"iteration":43,"passed_time":0.04424156018,"remaining_time":0.9612484439},
{"learn":[6.727122433],"iteration":44,"passed_time":0.04524106355,"remaining_time":0.9601159042},
{"learn":[6.671479784],"iteration":45,"passed_time":0.04637305918,"remaining_time":0.9617369231},
{"learn":[6.614101449],"iteration":46,"passed_time":0.04756648325,"remaining_time":0.9644863518},
{"learn":[6.56542259],"iteration":47,"passed_time":0.04877597141,"remaining_time":0.9673900997},
{"learn":[6.511621644],"iteration":48,"passed_time":0.04984755377,"remaining_time":0.967449462},
{"learn":[6.450221762],"iteration":49,"passed_time":0.0509000928,"remaining_time":0.9671017633},
{"learn":[6.402325366],"iteration":50,"passed_time":0.0519297155,"remaining_time":0.9663000002},
{"learn":[6.355080355],"iteration":51,"passed_time":0.0529304144,"remaining_time":0.9649621702},
{"learn":[6.307698777],"iteration":52,"passed_time":0.05393522754,"remaining_time":0.9637105751},
{"learn":[6.265652093],"iteration":53,"passed_time":0.05494706331,"remaining_time":0.9625911462},
{"learn":[6.234073213],"iteration":54,"passed_time":0.05603122239,"remaining_time":0.9627182756},
{"learn":[6.190817762],"iteration":55,"passed_time":0.05703606846,"remaining_time":0.9614651541},
{"learn":[6.150542248],"iteration":56,"passed_time":0.05808067233,"remaining_time":0.9608784913},
{"learn":[6.1160696],"iteration":57,"passed_time":0.05921396036,"remaining_time":0.9617163907},
{"learn":[6.086522091],"iteration":58,"passed_time":0.0605704161,"remaining_time":0.9660468059},
{"learn":[6.04881967],"iteration":59,"passed_time":0.06166072472,"remaining_time":0.9660180206},
{"learn":[6.013194031],"iteration":60,"passed_time":0.06270048063,"remaining_time":0.965176251},
{"learn":[5.978184671],"iteration":61,"passed_time":0.06369968991,"remaining_time":0.9637146634},
{"learn":[5.947737351],"iteration":62,"passed_time":0.06475215848,"remaining_time":0.9630598808},
{"learn":[5.919570125],"iteration":63,"passed_time":0.06575205704,"remaining_time":0.9616238342},
{"learn":[5.884162192],"iteration":64,"passed_time":0.06676640448,"remaining_time":0.9604090491},
{"learn":[5.851506193],"iteration":65,"passed_time":0.06777544598,"remaining_time":0.9591252507},
{"learn":[5.827012957],"iteration":66,"passed_time":0.06854299485,"remaining_time":0.954486779},
{"learn":[5.799957673],"iteration":67,"passed_time":0.06917803651,"remaining_time":0.9481460298},
{"learn":[5.780834844],"iteration":68,"passed_time":0.06986823874,"remaining_time":0.9427149314},
{"learn":[5.755249866],"iteration":69,"passed_time":0.07052152264,"remaining_time":0.9369288008},
{"learn":[5.736949294],"iteration":70,"passed_time":0.07121052207,"remaining_time":0.9317545775},
{"learn":[5.714862707],"iteration":71,"passed_time":0.07166477195,"remaining_time":0.9236792829},
{"learn":[5.692878581],"iteration":72,"passed_time":0.07229748231,"remaining_time":0.9180789877},
{"learn":[5.668914704],"iteration":73,"passed_time":0.07311201646,"remaining_time":0.914888206},
{"learn":[5.647102984],"iteration":74,"passed_time":0.07395151948,"remaining_time":0.9120687402},
{"learn":[5.629050994],"iteration":75,"passed_time":0.07471033514,"remaining_time":0.9083203903},
{"learn":[5.610177355],"iteration":76,"passed_time":0.07537217379,"remaining_time":0.9034872261},
{"learn":[5.592218543],"iteration":77,"passed_time":0.0761421294,"remaining_time":0.9000390167},
{"learn":[5.571207647],"iteration":78,"passed_time":0.07756311801,"remaining_time":0.9042485024},
{"learn":[5.5491964],"iteration":79,"passed_time":0.07893424894,"remaining_time":0.9077438628},
{"learn":[5.52525543],"iteration":80,"passed_time":0.08136258496,"remaining_time":0.9231137725},
{"learn":[5.509031236],"iteration":81,"passed_time":0.08216915522,"remaining_time":0.9198937134},
{"learn":[5.488921974],"iteration":82,"passed_time":0.0828097885,"remaining_time":0.9148985067},
{"learn":[5.475473773],"iteration":83,"passed_time":0.08345589391,"remaining_time":0.9100666526},
{"learn":[5.462470878],"iteration":84,"passed_time":0.08407805749,"remaining_time":0.90507556},
{"learn":[5.447074717],"iteration":85,"passed_time":0.08470631049,"remaining_time":0.9002507883},
{"learn":[5.430522051],"iteration":86,"passed_time":0.08563531678,"remaining_time":0.8986786692},
{"learn":[5.418775169],"iteration":87,"passed_time":0.08635458526,"remaining_time":0.89494752},
{"learn":[5.410321328],"iteration":88,"passed_time":0.0866349446,"remaining_time":0.8867913993},
{"learn":[5.39396909],"iteration":89,"passed_time":0.08733215798,"remaining_time":0.8830251529},
{"learn":[5.382034043],"iteration":90,"passed_time":0.08806304661,"remaining_time":0.8796627403},
{"learn":[5.367312135],"iteration":91,"passed_time":0.08880175515,"remaining_time":0.8764347138},
{"learn":[5.35725799],"iteration":92,"passed_time":0.08954660863,"remaining_time":0.8733201508},
{"learn":[5.348142095],"iteration":93,"passed_time":0.09060361995,"remaining_time":0.8732646774},
{"learn":[5.332895893],"iteration":94,"passed_time":0.09163015773,"remaining_time":0.8728978184},
{"learn":[5.321260542],"iteration":95,"passed_time":0.09231975147,"remaining_time":0.8693443264},
{"learn":[5.311553512],"iteration":96,"passed_time":0.09295679512,"remaining_time":0.8653606804},
{"learn":[5.304214023],"iteration":97,"passed_time":0.09358390928,"remaining_time":0.8613539405},
{"learn":[5.298419243],"iteration":98,"passed_time":0.09392205075,"remaining_time":0.8547855326},
{"learn":[5.293142089],"iteration":99,"passed_time":0.09429216151,"remaining_time":0.8486294535},
{"learn":[5.28674439],"iteration":100,"passed_time":0.09501369352,"remaining_time":0.8457159453},
{"learn":[5.275814803],"iteration":101,"passed_time":0.09563503455,"remaining_time":0.8419633434},
{"learn":[5.266086638],"iteration":102,"passed_time":0.09626513636,"remaining_time":0.838347838},
{"learn":[5.257797909],"iteration":103,"passed_time":0.09669542374,"remaining_time":0.8330682661},
{"learn":[5.246606125],"iteration":104,"passed_time":0.09743897946,"remaining_time":0.8305513011},
{"learn":[5.239784482],"iteration":105,"passed_time":0.09818323174,"remaining_time":0.8280736714},
{"learn":[5.2296703],"iteration":106,"passed_time":0.09880778713,"remaining_time":0.8246294757},
{"learn":[5.218561997],"iteration":107,"passed_time":0.09943922078,"remaining_time":0.821294305},
{"learn":[5.210617097],"iteration":108,"passed_time":0.100114397,"remaining_time":0.8183663098},
{"learn":[5.198641162],"iteration":109,"passed_time":0.1008136093,"remaining_time":0.8156737483},
{"learn":[5.190086287],"iteration":110,"passed_time":0.101770432,"remaining_time":0.8150803066},
{"learn":[5.179357516],"iteration":111,"passed_time":0.102600411,"remaining_time":0.8134746875},
{"learn":[5.171035937],"iteration":112,"passed_time":0.1032276431,"remaining_time":0.8102913227},
{"learn":[5.163536719],"iteration":113,"passed_time":0.1038618186,"remaining_time":0.8072067656},
{"learn":[5.15398743],"iteration":114,"passed_time":0.104458805,"remaining_time":0.8038786298},
{"learn":[5.143410261],"iteration":115,"passed_time":0.1050768206,"remaining_time":0.8007578401},
{"learn":[5.134404406],"iteration":116,"passed_time":0.10569416,"remaining_time":0.797674729},
{"learn":[5.126746174],"iteration":117,"passed_time":0.1062870429,"remaining_time":0.7944506087},
{"learn":[5.118277336],"iteration":118,"passed_time":0.1068972183,"remaining_time":0.791398734},
{"learn":[5.114136586],"iteration":119,"passed_time":0.1075105553,"remaining_time":0.7884107386},
{"learn":[5.104725337],"iteration":120,"passed_time":0.1081320005,"remaining_time":0.7855208959},
{"learn":[5.095312749],"iteration":121,"passed_time":0.1087675767,"remaining_time":0.7827699373},
{"learn":[5.089181195],"iteration":122,"passed_time":0.1094490028,"remaining_time":0.7803802886},
{"learn":[5.083154299],"iteration":123,"passed_time":0.1102069573,"remaining_time":0.7785588272},
{"learn":[5.07616167],"iteration":124,"passed_time":0.110827171,"remaining_time":0.7757901967},
{"learn":[5.065345076],"iteration":125,"passed_time":0.1114553114,"remaining_time":0.773110652},
{"learn":[5.058954331],"iteration":126,"passed_time":0.1120715364,"remaining_time":0.7703815062},
{"learn":[5.05042487],"iteration":127,"passed_time":0.1127022325,"remaining_time":0.7677839592},
{"learn":[5.040112441],"iteration":128,"passed_time":0.113308993,"remaining_time":0.7650552936},
{"learn":[5.034967672],"iteration":129,"passed_time":0.1139086492,"remaining_time":0.7623117292},
{"learn":[5.030214499],"iteration":130,"passed_time":0.1142316016,"remaining_time":0.7577653569},
{"learn":[5.021496711],"iteration":131,"passed_time":0.1148461271,"remaining_time":0.7552002905},
{"learn":[5.011936882],"iteration":132,"passed_time":0.1155946572,"remaining_time":0.7535381035},
{"learn":[5.00414759],"iteration":133,"passed_time":0.1162916661,"remaining_time":0.7515565881},
{"learn":[4.996530258],"iteration":134,"passed_time":0.117042926,"remaining_time":0.7499417113},
{"learn":[4.988217366],"iteration":135,"passed_time":0.1177133202,"remaining_time":0.747825799},
{"learn":[4.980468478],"iteration":136,"passed_time":0.1183365361,"remaining_time":0.7454338004},
{"learn":[4.971042264],"iteration":137,"passed_time":0.1189388974,"remaining_time":0.7429371705},
{"learn":[4.963839334],"iteration":138,"passed_time":0.1195444745,"remaining_time":0.7404877163},
{"learn":[4.959726957],"iteration":139,"passed_time":0.120184031,"remaining_time":0.7382733332},
{"learn":[4.954438865],"iteration":140,"passed_time":0.1207807371,"remaining_time":0.7358202352},
{"learn":[4.949237581],"iteration":141,"passed_time":0.1213804454,"remaining_time":0.7334114236},
{"learn":[4.943760273],"iteration":142,"passed_time":0.1219828855,"remaining_time":0.7310442861},
{"learn":[4.937008907],"iteration":143,"passed_time":0.122573323,"remaining_time":0.728630309},
{"learn":[4.932641305],"iteration":144,"passed_time":0.1231693789,"remaining_time":0.7262746134},
{"learn":[4.920522849],"iteration":145,"passed_time":0.1238139372,"remaining_time":0.7242267288},
{"learn":[4.917876611],"iteration":146,"passed_time":0.1241252905,"remaining_time":0.720264441},
{"learn":[4.911482046],"iteration":147,"passed_time":0.124830786,"remaining_time":0.7186204708},
{"learn":[4.906242301],"iteration":148,"passed_time":0.1255639435,"remaining_time":0.7171470869},
{"learn":[4.897786139],"iteration":149,"passed_time":0.1261991468,"remaining_time":0.7151284985},
{"learn":[4.891737092],"iteration":150,"passed_time":0.1268477819,"remaining_time":0.7132037537},
{"learn":[4.886579731],"iteration":151,"passed_time":0.127490594,"remaining_time":0.7112633141},
{"learn":[4.879167279],"iteration":152,"passed_time":0.1280935083,"remaining_time":0.7091189641},
{"learn":[4.87363046],"iteration":153,"passed_time":0.1287097716,"remaining_time":0.707067966},
{"learn":[4.869913937],"iteration":154,"passed_time":0.1293094355,"remaining_time":0.704944987},
{"learn":[4.866061307],"iteration":155,"passed_time":0.1299135988,"remaining_time":0.7028658809},
{"learn":[4.861809134],"iteration":156,"passed_time":0.130623989,"remaining_time":0.7013759409},
{"learn":[4.856494585],"iteration":157,"passed_time":0.131606608,"remaining_time":0.7013466073},
{"learn":[4.850424252],"iteration":158,"passed_time":0.1323038237,"remaining_time":0.6997956964},
{"learn":[4.845729519],"iteration":159,"passed_time":0.1329198618,"remaining_time":0.6978292747},
{"learn":[4.838186023],"iteration":160,"passed_time":0.1335240581,"remaining_time":0.6958179179},
{"learn":[4.829955361],"iteration":161,"passed_time":0.1341222041,"remaining_time":0.6937926359},
{"learn":[4.82374619],"iteration":162,"passed_time":0.1347221429,"remaining_time":0.6917940712},
{"learn":[4.819636193],"iteration":163,"passed_time":0.1353351812,"remaining_time":0.6898793381},
{"learn":[4.817321483],"iteration":164,"passed_time":0.1359268609,"remaining_time":0.6878722958},
{"learn":[4.813337194],"iteration":165,"passed_time":0.1365234383,"remaining_time":0.6859069128},
{"learn":[4.809571394],"iteration":166,"passed_time":0.1371129728,"remaining_time":0.6839227924},
{"learn":[4.803288961],"iteration":167,"passed_time":0.1377278721,"remaining_time":0.6820808904},
{"learn":[4.797704904],"iteration":168,"passed_time":0.1383399752,"remaining_time":0.6802397598},
{"learn":[4.791545638],"iteration":169,"passed_time":0.13898394,"remaining_time":0.6785686484},
{"learn":[4.789036571],"iteration":170,"passed_time":0.139703619,"remaining_time":0.6772766092},
{"learn":[4.78111073],"iteration":171,"passed_time":0.140378466,"remaining_time":0.6757754059},
{"learn":[4.778131294],"iteration":172,"passed_time":0.1409820427,"remaining_time":0.6739430594},
{"learn":[4.772286642],"iteration":173,"passed_time":0.1416705937,"remaining_time":0.6725282206},
{"learn":[4.767485233],"iteration":174,"passed_time":0.142613219,"remaining_time":0.6723194611},
{"learn":[4.762813688],"iteration":175,"passed_time":0.1432838254,"remaining_time":0.6708288187},
{"learn":[4.756441484],"iteration":176,"passed_time":0.1439090218,"remaining_time":0.669136299},
{"learn":[4.751856625],"iteration":177,"passed_time":0.1445344947,"remaining_time":0.6674570484},
{"learn":[4.748547501],"iteration":178,"passed_time":0.145138233,"remaining_time":0.6656898842},
{"learn":[4.743916045],"iteration":179,"passed_time":0.1459015393,"remaining_time":0.664662568},
{"learn":[4.739667726],"iteration":180,"passed_time":0.1466656632,"remaining_time":0.6636418683},
{"learn":[4.735269178],"iteration":181,"passed_time":0.1474254117,"remaining_time":0.6626043229},
{"learn":[4.729293086],"iteration":182,"passed_time":0.1482659123,"remaining_time":0.6619303296},
{"learn":[4.724598786],"iteration":183,"passed_time":0.1489588329,"remaining_time":0.6606000417},
{"learn":[4.719073028],"iteration":184,"passed_time":0.1496444606,"remaining_time":0.6592445157},
{"learn":[4.713853326],"iteration":185,"passed_time":0.1503252553,"remaining_time":0.657875042},
{"learn":[4.707455351],"iteration":186,"passed_time":0.1509434624,"remaining_time":0.6562408285},
{"learn":[4.697857688],"iteration":187,"passed_time":0.1517272994,"remaining_time":0.6553328037},
{"learn":[4.694310635],"iteration":188,"passed_time":0.1524366648,"remaining_time":0.6541065352},
{"learn":[4.690914753],"iteration":189,"passed_time":0.1531629835,"remaining_time":0.6529579822},
{"learn":[4.687878984],"iteration":190,"passed_time":0.154042579,"remaining_time":0.6524630701},
{"learn":[4.683036798],"iteration":191,"passed_time":0.1549093492,"remaining_time":0.651910178},
{"learn":[4.677589896],"iteration":192,"passed_time":0.1558442492,"remaining_time":0.6516389075},
{"learn":[4.674613724],"iteration":193,"passed_time":0.1566950423,"remaining_time":0.6510113614},
{"learn":[4.671942595],"iteration":194,"passed_time":0.1575264861,"remaining_time":0.6503016477},
{"learn":[4.667964107],"iteration":195,"passed_time":0.1581741899,"remaining_time":0.6488369829},
{"learn":[4.662104573],"iteration":196,"passed_time":0.1588088348,"remaining_time":0.6473273825},
{"learn":[4.657013265],"iteration":197,"passed_time":0.1594372027,"remaining_time":0.6458011948},
{"learn":[4.653152312],"iteration":198,"passed_time":0.1600752408,"remaining_time":0.6443229543},
{"learn":[4.648010312],"iteration":199,"passed_time":0.1608804,"remaining_time":0.6435215999},
{"learn":[4.642185059],"iteration":200,"passed_time":0.1616410265,"remaining_time":0.6425431851},
{"learn":[4.636988546],"iteration":201,"passed_time":0.1623138129,"remaining_time":0.6412199143},
{"learn":[4.630378051],"iteration":202,"passed_time":0.1630487472,"remaining_time":0.640147052},
{"learn":[4.627614411],"iteration":203,"passed_time":0.1638230871,"remaining_time":0.6392312613},
{"learn":[4.623785212],"iteration":204,"passed_time":0.1645879332,"remaining_time":0.6382800335},
{"learn":[4.620823344],"iteration":205,"passed_time":0.1652663085,"remaining_time":0.6369973249},
{"learn":[4.616072985],"iteration":206,"passed_time":0.165927454,"remaining_time":0.6356544494},
{"learn":[4.61299408],"iteration":207,"passed_time":0.1666036711,"remaining_time":0.6343755168},
{"learn":[4.608244949],"iteration":208,"passed_time":0.1673046698,"remaining_time":0.6331961425},
{"learn":[4.605148129],"iteration":209,"passed_time":0.1679206099,"remaining_time":0.631701342},
{"learn":[4.600958744],"iteration":210,"passed_time":0.1685425407,"remaining_time":0.6302372729},
{"learn":[4.59742399],"iteration":211,"passed_time":0.1691683636,"remaining_time":0.6287956155},
{"learn":[4.594796813],"iteration":212,"passed_time":0.1698019118,"remaining_time":0.6273901623},
{"learn":[4.592159832],"iteration":213,"passed_time":0.1705075888,"remaining_time":0.6262568447},
{"learn":[4.588823946],"iteration":214,"passed_time":0.1711062877,"remaining_time":0.6247369108},
{"learn":[4.584854242],"iteration":215,"passed_time":0.1717158558,"remaining_time":0.6232649579},
{"learn":[4.580042661],"iteration":216,"passed_time":0.1723334019,"remaining_time":0.6218297405},
{"learn":[4.577133477],"iteration":217,"passed_time":0.1729218856,"remaining_time":0.6202977733},
{"learn":[4.572689296],"iteration":218,"passed_time":0.1735103655,"remaining_time":0.6187744086},
{"learn":[4.567859817],"iteration":219,"passed_time":0.1741864053,"remaining_time":0.6175699825},
{"learn":[4.562211319],"iteration":220,"passed_time":0.1748022214,"remaining_time":0.6161580564},
{"learn":[4.560917817],"iteration":221,"passed_time":0.1754132714,"remaining_time":0.6147365999},
{"learn":[4.555930704],"iteration":222,"passed_time":0.1761356057,"remaining_time":0.6137101597},
{"learn":[4.553988183],"iteration":223,"passed_time":0.1768005986,"remaining_time":0.6124877879},
{"learn":[4.551541901],"iteration":224,"passed_time":0.177429606,"remaining_time":0.6111464205},
{"learn":[4.548846269],"iteration":225,"passed_time":0.1781656826,"remaining_time":0.6101780457},
{"learn":[4.544989508],"iteration":226,"passed_time":0.1788326817,"remaining_time":0.6089764887},
{"learn":[4.541838957],"iteration":227,"passed_time":0.1795232959,"remaining_time":0.607859581},
{"learn":[4.540350727],"iteration":228,"passed_time":0.1802315738,"remaining_time":0.6068058664},
{"learn":[4.533727083],"iteration":229,"passed_time":0.1808528053,"remaining_time":0.6054637396},
{"learn":[4.52999736],"iteration":230,"passed_time":0.1817169081,"remaining_time":0.6049363736},
{"learn":[4.528116482],"iteration":231,"passed_time":0.1823992793,"remaining_time":0.6038045107},
{"learn":[4.527022827],"iteration":232,"passed_time":0.1830645517,"remaining_time":0.6026202196},
{"learn":[4.52294239],"iteration":233,"passed_time":0.1837335267,"remaining_time":0.6014524849},
{"learn":[4.518272752],"iteration":234,"passed_time":0.1847966309,"remaining_time":0.6015720113},
{"learn":[4.511316218],"iteration":235,"passed_time":0.185628746,"remaining_time":0.600933737},
{"learn":[4.505644317],"iteration":236,"passed_time":0.1864553671,"remaining_time":0.6002761396},
{"learn":[4.501615867],"iteration":237,"passed_time":0.1872103561,"remaining_time":0.5993877787},
{"learn":[4.49879244],"iteration":238,"passed_time":0.1878529814,"remaining_time":0.5981427566},
{"learn":[4.496729928],"iteration":239,"passed_time":0.1885957862,"remaining_time":0.5972199895},
{"learn":[4.492933145],"iteration":240,"passed_time":0.1892486101,"remaining_time":0.5960153324},
{"learn":[4.486944581],"iteration":241,"passed_time":0.1899200742,"remaining_time":0.594873621},
{"learn":[4.485207615],"iteration":242,"passed_time":0.190512462,"remaining_time":0.5934894392},
{"learn":[4.480229219],"iteration":243,"passed_time":0.1914393618,"remaining_time":0.5931481864},
{"learn":[4.478978381],"iteration":244,"passed_time":0.1922371575,"remaining_time":0.5924043016},
{"learn":[4.472170535],"iteration":245,"passed_time":0.1929960175,"remaining_time":0.5915406391},
{"learn":[4.471041398],"iteration":246,"passed_time":0.1937119924,"remaining_time":0.5905470861},
{"learn":[4.467319559],"iteration":247,"passed_time":0.1944499347,"remaining_time":0.5896223826},
{"learn":[4.459291314],"iteration":248,"passed_time":0.195093713,"remaining_time":0.5884151746},
{"learn":[4.458235384],"iteration":249,"passed_time":0.1957950674,"remaining_time":0.5873852023},
{"learn":[4.45699887],"iteration":250,"passed_time":0.1964883274,"remaining_time":0.5863336941},
{"learn":[4.448608311],"iteration":251,"passed_time":0.1971883844,"remaining_time":0.5853052046},
{"learn":[4.445473718],"iteration":252,"passed_time":0.1978567422,"remaining_time":0.584185717},
{"learn":[4.442389214],"iteration":253,"passed_time":0.1985078701,"remaining_time":0.5830191777},
{"learn":[4.438271328],"iteration":254,"passed_time":0.1992665847,"remaining_time":0.5821710024},
{"learn":[4.436576541],"iteration":255,"passed_time":0.1999937164,"remaining_time":0.5812317382},
{"learn":[4.432478475],"iteration":256,"passed_time":0.2007078711,"remaining_time":0.580256608},
{"learn":[4.428530454],"iteration":257,"passed_time":0.2016808379,"remaining_time":0.5800278362},
{"learn":[4.424288499],"iteration":258,"passed_time":0.202698855,"remaining_time":0.5799222069},
{"learn":[4.420109414],"iteration":259,"passed_time":0.2035754709,"remaining_time":0.5794071095},
{"learn":[4.419250475],"iteration":260,"passed_time":0.2042658956,"remaining_time":0.5783620569},
{"learn":[4.416136393],"iteration":261,"passed_time":0.2048754247,"remaining_time":0.577091845},
{"learn":[4.41466654],"iteration":262,"passed_time":0.2055464285,"remaining_time":0.5759989269},
{"learn":[4.40913278],"iteration":263,"passed_time":0.2064331707,"remaining_time":0.5755106576},
{"learn":[4.405383892],"iteration":264,"passed_time":0.2071452139,"remaining_time":0.5745348386},
{"learn":[4.402723494],"iteration":265,"passed_time":0.2078096274,"remaining_time":0.5734295735},
{"learn":[4.397656301],"iteration":266,"passed_time":0.208511853,"remaining_time":0.5724314168},
{"learn":[4.394554693],"iteration":267,"passed_time":0.2092069955,"remaining_time":0.5714161221},
{"learn":[4.393290659],"iteration":268,"passed_time":0.2099253488,"remaining_time":0.5704662824},
{"learn":[4.390381743],"iteration":269,"passed_time":0.2106762836,"remaining_time":0.5696062484},
{"learn":[4.389332833],"iteration":270,"passed_time":0.2113512321,"remaining_time":0.5685426132},
{"learn":[4.388150521],"iteration":271,"passed_time":0.2120743341,"remaining_time":0.5676107177},
{"learn":[4.383377867],"iteration":272,"passed_time":0.2129686772,"remaining_time":0.5671363674},
{"learn":[4.382416208],"iteration":273,"passed_time":0.2141495203,"remaining_time":0.567418072},
{"learn":[4.379995623],"iteration":274,"passed_time":0.2150426299,"remaining_time":0.5669305698},
{"learn":[4.376206947],"iteration":275,"passed_time":0.2156941998,"remaining_time":0.5658065241},
{"learn":[4.367041717],"iteration":276,"passed_time":0.2165030799,"remaining_time":0.5650964866},
{"learn":[4.366532579],"iteration":277,"passed_time":0.2172696236,"remaining_time":0.564275785},
{"learn":[4.362582871],"iteration":278,"passed_time":0.2182184012,"remaining_time":0.5639264059},
{"learn":[4.36146873],"iteration":279,"passed_time":0.2189037118,"remaining_time":0.5628952589},
{"learn":[4.357062952],"iteration":280,"passed_time":0.2195893337,"remaining_time":0.56186737},
{"learn":[4.353837015],"iteration":281,"passed_time":0.2202864376,"remaining_time":0.5608711425},
{"learn":[4.352995974],"iteration":282,"passed_time":0.2210089603,"remaining_time":0.5599414293},
{"learn":[4.351561516],"iteration":283,"passed_time":0.2217009493,"remaining_time":0.558936196},
{"learn":[4.350893581],"iteration":284,"passed_time":0.2224929948,"remaining_time":0.55818418},
{"learn":[4.349860304],"iteration":285,"passed_time":0.2231967552,"remaining_time":0.5572114798},
{"learn":[4.344220157],"iteration":286,"passed_time":0.2239034271,"remaining_time":0.5562478868},
{"learn":[4.343584661],"iteration":287,"passed_time":0.2245365234,"remaining_time":0.5551041829},
{"learn":[4.33752683],"iteration":288,"passed_time":0.2251900681,"remaining_time":0.5540143198},
{"learn":[4.335700072],"iteration":289,"passed_time":0.2258615766,"remaining_time":0.5529714462},
{"learn":[4.331231205],"iteration":290,"passed_time":0.2265008765,"remaining_time":0.5518526511},
{"learn":[4.327686277],"iteration":291,"passed_time":0.227286012,"remaining_time":0.5510907415},
{"learn":[4.32221782],"iteration":292,"passed_time":0.2280280138,"remaining_time":0.550224593},
{"learn":[4.318354198],"iteration":293,"passed_time":0.2288397499,"remaining_time":0.5495267463},
{"learn":[4.317477698],"iteration":294,"passed_time":0.2295303794,"remaining_time":0.5485387034},
{"learn":[4.313156872],"iteration":295,"passed_time":0.2301625269,"remaining_time":0.5474135775},
{"learn":[4.304885831],"iteration":296,"passed_time":0.2310188809,"remaining_time":0.546822469},
{"learn":[4.301691235],"iteration":297,"passed_time":0.2320174243,"remaining_time":0.5465645364},
{"learn":[4.297282885],"iteration":298,"passed_time":0.2327598155,"remaining_time":0.5457011059},
{"learn":[4.292050941],"iteration":299,"passed_time":0.2336103838,"remaining_time":0.5450908955},
{"learn":[4.289978473],"iteration":300,"passed_time":0.2343120951,"remaining_time":0.5441334036},
{"learn":[4.287810512],"iteration":301,"passed_time":0.2349306614,"remaining_time":0.542985436},
{"learn":[4.282343416],"iteration":302,"passed_time":0.2356800427,"remaining_time":0.5421418804},
{"learn":[4.274726309],"iteration":303,"passed_time":0.2366407644,"remaining_time":0.5417828027},
{"learn":[4.274016524],"iteration":304,"passed_time":0.2370641138,"remaining_time":0.5401952756},
{"learn":[4.271454395],"iteration":305,"passed_time":0.2378458032,"remaining_time":0.5394280636},
{"learn":[4.267006125],"iteration":306,"passed_time":0.2387187705,"remaining_time":0.5388668012},
{"learn":[4.259058707],"iteration":307,"passed_time":0.2394751297,"remaining_time":0.5380415251},
{"learn":[4.251068305],"iteration":308,"passed_time":0.2402693805,"remaining_time":0.5373014303},
{"learn":[4.250393876],"iteration":309,"passed_time":0.241000561,"remaining_time":0.5364206034},
{"learn":[4.247419577],"iteration":310,"passed_time":0.2416631938,"remaining_time":0.5353888763},
{"learn":[4.242832935],"iteration":311,"passed_time":0.2422865912,"remaining_time":0.534272996},
{"learn":[4.240011894],"iteration":312,"passed_time":0.24291353,"remaining_time":0.5331680355},
{"learn":[4.234968725],"iteration":313,"passed_time":0.2435271825,"remaining_time":0.5320370929},
{"learn":[4.23083056],"iteration":314,"passed_time":0.2441410019,"remaining_time":0.5309097978},
{"learn":[4.222973373],"iteration":315,"passed_time":0.2448173791,"remaining_time":0.5299211623},
{"learn":[4.219206319],"iteration":316,"passed_time":0.2461672219,"remaining_time":0.5303855286},
{"learn":[4.214391568],"iteration":317,"passed_time":0.2471322795,"remaining_time":0.5300132536},
{"learn":[4.211345015],"iteration":318,"passed_time":0.2478559299,"remaining_time":0.5291219069},
{"learn":[4.209359632],"iteration":319,"passed_time":0.2485277931,"remaining_time":0.5281215602},
{"learn":[4.205632501],"iteration":320,"passed_time":0.2491563693,"remaining_time":0.527031697},
{"learn":[4.199771046],"iteration":321,"passed_time":0.2497622918,"remaining_time":0.5258969996},
{"learn":[4.195522106],"iteration":322,"passed_time":0.2504225191,"remaining_time":0.5248793976},
{"learn":[4.193031878],"iteration":323,"passed_time":0.2510343396,"remaining_time":0.5237630049},
{"learn":[4.187971848],"iteration":324,"passed_time":0.2516921123,"remaining_time":0.5227451562},
{"learn":[4.180083175],"iteration":325,"passed_time":0.2523344182,"remaining_time":0.5216975395},
{"learn":[4.1795409],"iteration":326,"passed_time":0.2530777078,"remaining_time":0.5208602365},
{"learn":[4.179018884],"iteration":327,"passed_time":0.2536816797,"remaining_time":0.5197380754},
{"learn":[4.174825584],"iteration":328,"passed_time":0.2543565228,"remaining_time":0.5187636073},
{"learn":[4.168658323],"iteration":329,"passed_time":0.255038217,"remaining_time":0.5178048648},
{"learn":[4.162228736],"iteration":330,"passed_time":0.2557885434,"remaining_time":0.5169865121},
{"learn":[4.153969441],"iteration":331,"passed_time":0.2565321998,"remaining_time":0.516155149},
{"learn":[4.147350451],"iteration":332,"passed_time":0.2573886013,"remaining_time":0.5155501414},
{"learn":[4.143011365],"iteration":333,"passed_time":0.2580586049,"remaining_time":0.5145719487},
{"learn":[4.14041656],"iteration":334,"passed_time":0.2586893523,"remaining_time":0.5135176696},
{"learn":[4.134434676],"iteration":335,"passed_time":0.2593561155,"remaining_time":0.5125370855},
{"learn":[4.128845541],"iteration":336,"passed_time":0.2600864351,"remaining_time":0.511683402},
{"learn":[4.127025349],"iteration":337,"passed_time":0.2608323401,"remaining_time":0.5108609739},
{"learn":[4.121202728],"iteration":338,"passed_time":0.2615530948,"remaining_time":0.5099899577},
{"learn":[4.117986284],"iteration":339,"passed_time":0.2626767421,"remaining_time":0.5099019111},
{"learn":[4.114866743],"iteration":340,"passed_time":0.263342502,"remaining_time":0.5089228997},
{"learn":[4.107523787],"iteration":341,"passed_time":0.2639974348,"remaining_time":0.5079248892},
{"learn":[4.101206387],"iteration":342,"passed_time":0.2646327001,"remaining_time":0.5068912069},
{"learn":[4.09977987],"iteration":343,"passed_time":0.2653307429,"remaining_time":0.5059795562},
{"learn":[4.096829812],"iteration":344,"passed_time":0.2662146345,"remaining_time":0.5054219873},
{"learn":[4.090339688],"iteration":345,"passed_time":0.2671978609,"remaining_time":0.505050292},
{"learn":[4.087644061],"iteration":346,"passed_time":0.2680332148,"remaining_time":0.5043967991},
{"learn":[4.081934717],"iteration":347,"passed_time":0.2689516299,"remaining_time":0.5038978813},
{"learn":[4.078518419],"iteration":348,"passed_time":0.2703267832,"remaining_time":0.5042485268},
{"learn":[4.075144833],"iteration":349,"passed_time":0.271053674,"remaining_time":0.5033853945},
{"learn":[4.070892481],"iteration":350,"passed_time":0.2720206026,"remaining_time":0.5029668693},
{"learn":[4.065140579],"iteration":351,"passed_time":0.2726843177,"remaining_time":0.5019870393},
{"learn":[4.0611358],"iteration":352,"passed_time":0.2733673203,"remaining_time":0.501044352},
{"learn":[4.058198699],"iteration":353,"passed_time":0.274002156,"remaining_time":0.5000152338},
{"learn":[4.052904888],"iteration":354,"passed_time":0.2746654241,"remaining_time":0.499039996},
{"learn":[4.049000636],"iteration":355,"passed_time":0.2753474634,"remaining_time":0.4981004674},
{"learn":[4.0458885],"iteration":356,"passed_time":0.2759889069,"remaining_time":0.4970892637},
{"learn":[4.041121496],"iteration":357,"passed_time":0.2765895082,"remaining_time":0.4960068835},
{"learn":[4.035675325],"iteration":358,"passed_time":0.2771989591,"remaining_time":0.4949429883},
{"learn":[4.032523093],"iteration":359,"passed_time":0.2778513968,"remaining_time":0.4939580387},
{"learn":[4.032101014],"iteration":360,"passed_time":0.2784391713,"remaining_time":0.4928604722},
{"learn":[4.026129119],"iteration":361,"passed_time":0.2790452639,"remaining_time":0.4917980065},
{"learn":[4.024410665],"iteration":362,"passed_time":0.2796556538,"remaining_time":0.4907455963},
{"learn":[4.018310166],"iteration":363,"passed_time":0.2803395774,"remaining_time":0.4898240968},
{"learn":[4.01160424],"iteration":364,"passed_time":0.281119093,"remaining_time":0.4890702028},
{"learn":[4.004794697],"iteration":365,"passed_time":0.2817751332,"remaining_time":0.4881022799},
{"learn":[4.003376056],"iteration":366,"passed_time":0.2823839163,"remaining_time":0.4870545477},
{"learn":[3.997879499],"iteration":367,"passed_time":0.2830167492,"remaining_time":0.4860505041},
{"learn":[3.992789036],"iteration":368,"passed_time":0.2836148178,"remaining_time":0.4849890244},
{"learn":[3.990938752],"iteration":369,"passed_time":0.284200055,"remaining_time":0.4839082017},
{"learn":[3.9905071],"iteration":370,"passed_time":0.2848330372,"remaining_time":0.4829109984},
{"learn":[3.986283995],"iteration":371,"passed_time":0.2854244596,"remaining_time":0.4818455931},
{"learn":[3.983215817],"iteration":372,"passed_time":0.2862905555,"remaining_time":0.4812444458},
{"learn":[3.978366862],"iteration":373,"passed_time":0.2883899849,"remaining_time":0.4827062314},
{"learn":[3.975593307],"iteration":374,"passed_time":0.28913157,"remaining_time":0.48188595},
{"learn":[3.972301353],"iteration":375,"passed_time":0.2898062347,"remaining_time":0.4809550278},
{"learn":[3.971795493],"iteration":376,"passed_time":0.2904903483,"remaining_time":0.4800410795},
{"learn":[3.970177303],"iteration":377,"passed_time":0.2910990632,"remaining_time":0.4790042786},
{"learn":[3.967439294],"iteration":378,"passed_time":0.2917114233,"remaining_time":0.4779757093},
{"learn":[3.964136042],"iteration":379,"passed_time":0.2923885862,"remaining_time":0.4770550617},
{"learn":[3.958918704],"iteration":380,"passed_time":0.2930405007,"remaining_time":0.4760946717},
{"learn":[3.956388194],"iteration":381,"passed_time":0.2938767162,"remaining_time":0.4754340592},
{"learn":[3.953587596],"iteration":382,"passed_time":0.2945279905,"remaining_time":0.4744745956},
{"learn":[3.951385877],"iteration":383,"passed_time":0.2952485196,"remaining_time":0.4736278335},
{"learn":[3.94732233],"iteration":384,"passed_time":0.296386113,"remaining_time":0.4734479467},
{"learn":[3.946834043],"iteration":385,"passed_time":0.2972006479,"remaining_time":0.4727492171},
{"learn":[3.946323178],"iteration":386,"passed_time":0.2978579063,"remaining_time":0.4718007662},
{"learn":[3.94330111],"iteration":387,"passed_time":0.29850264,"remaining_time":0.470834061},
{"learn":[3.938486437],"iteration":388,"passed_time":0.2991228253,"remaining_time":0.4698304532},
{"learn":[3.934455994],"iteration":389,"passed_time":0.2998475709,"remaining_time":0.4689923545},
{"learn":[3.931784263],"iteration":390,"passed_time":0.3004884899,"remaining_time":0.468024272},
{"learn":[3.929397325],"iteration":391,"passed_time":0.3012189393,"remaining_time":0.4671967221},
{"learn":[3.928391456],"iteration":392,"passed_time":0.3019120484,"remaining_time":0.4663119933},
{"learn":[3.92472048],"iteration":393,"passed_time":0.3026508434,"remaining_time":0.4654985054},
{"learn":[3.921517636],"iteration":394,"passed_time":0.3034466919,"remaining_time":0.4647727813},
{"learn":[3.918404319],"iteration":395,"passed_time":0.3041835164,"remaining_time":0.4639566766},
{"learn":[3.914684588],"iteration":396,"passed_time":0.3049580569,"remaining_time":0.4631982577},
{"learn":[3.909591597],"iteration":397,"passed_time":0.3057652625,"remaining_time":0.4624891658},
{"learn":[3.903217874],"iteration":398,"passed_time":0.3064178341,"remaining_time":0.4615466624},
{"learn":[3.900058737],"iteration":399,"passed_time":0.3072045059,"remaining_time":0.4608067589},
{"learn":[3.896965556],"iteration":400,"passed_time":0.3079466915,"remaining_time":0.4600001701},
{"learn":[3.895609623],"iteration":401,"passed_time":0.3086174771,"remaining_time":0.4590876898},
{"learn":[3.892219414],"iteration":402,"passed_time":0.3092241716,"remaining_time":0.4580814651},
{"learn":[3.886880267],"iteration":403,"passed_time":0.309856908,"remaining_time":0.4571156366},
{"learn":[3.880878543],"iteration":404,"passed_time":0.3105421899,"remaining_time":0.4562286494},
{"learn":[3.878885027],"iteration":405,"passed_time":0.3112943858,"remaining_time":0.4554405546},
{"learn":[3.875239564],"iteration":406,"passed_time":0.3121276064,"remaining_time":0.4547706894},
{"learn":[3.868186748],"iteration":407,"passed_time":0.3128175754,"remaining_time":0.4538921682},
{"learn":[3.865738982],"iteration":408,"passed_time":0.3135375764,"remaining_time":0.453057965},
{"learn":[3.861879736],"iteration":409,"passed_time":0.3148476132,"remaining_time":0.4530733947},
{"learn":[3.856077972],"iteration":410,"passed_time":0.3157058797,"remaining_time":0.4524349468},
{"learn":[3.85088309],"iteration":411,"passed_time":0.3165237836,"remaining_time":0.4517378271},
{"learn":[3.846603922],"iteration":412,"passed_time":0.3172825936,"remaining_time":0.4509561318},
{"learn":[3.843087206],"iteration":413,"passed_time":0.3179067936,"remaining_time":0.4499840122},
{"learn":[3.83730804],"iteration":414,"passed_time":0.3185436335,"remaining_time":0.449031387},
{"learn":[3.833863863],"iteration":415,"passed_time":0.3191773226,"remaining_time":0.4480758568},
{"learn":[3.831282666],"iteration":416,"passed_time":0.3198783711,"remaining_time":0.447216044},
{"learn":[3.828491706],"iteration":417,"passed_time":0.3205349582,"remaining_time":0.4462950853},
{"learn":[3.825755473],"iteration":418,"passed_time":0.3211920144,"remaining_time":0.445376039},
{"learn":[3.825364465],"iteration":419,"passed_time":0.3218519334,"remaining_time":0.4444621937},
{"learn":[3.819548276],"iteration":420,"passed_time":0.3224801994,"remaining_time":0.4435060225},
{"learn":[3.81546404],"iteration":421,"passed_time":0.3231194342,"remaining_time":0.4425664288},
{"learn":[3.811624758],"iteration":422,"passed_time":0.323771446,"remaining_time":0.441645684},
{"learn":[3.807931787],"iteration":423,"passed_time":0.3243826745,"remaining_time":0.4406708031},
{"learn":[3.804681395],"iteration":424,"passed_time":0.3249897374,"remaining_time":0.4396919977},
{"learn":[3.802620359],"iteration":425,"passed_time":0.3256612268,"remaining_time":0.4388017469},
{"learn":[3.800558159],"iteration":426,"passed_time":0.3263350831,"remaining_time":0.437915697},
{"learn":[3.797994671],"iteration":427,"passed_time":0.3270803234,"remaining_time":0.4371260396},
{"learn":[3.796124901],"iteration":428,"passed_time":0.3277809674,"remaining_time":0.4362772317},
{"learn":[3.793152662],"iteration":429,"passed_time":0.3284709334,"remaining_time":0.4354149582},
{"learn":[3.788603844],"iteration":430,"passed_time":0.3291775566,"remaining_time":0.434575475},
{"learn":[3.780792961],"iteration":431,"passed_time":0.329825916,"remaining_time":0.4336600006},
{"learn":[3.777656467],"iteration":432,"passed_time":0.3304398664,"remaining_time":0.4327007026},
{"learn":[3.774234491],"iteration":433,"passed_time":0.3310878198,"remaining_time":0.4317873411},
{"learn":[3.772041818],"iteration":434,"passed_time":0.3317278626,"remaining_time":0.430864925},
{"learn":[3.76972094],"iteration":435,"passed_time":0.3323376145,"remaining_time":0.4299046206},
{"learn":[3.766536629],"iteration":436,"passed_time":0.3329488622,"remaining_time":0.4289478476},
{"learn":[3.765349043],"iteration":437,"passed_time":0.3335632384,"remaining_time":0.4279966666},
{"learn":[3.760993052],"iteration":438,"passed_time":0.3341561948,"remaining_time":0.4270196476},
{"learn":[3.755848708],"iteration":439,"passed_time":0.3349057611,"remaining_time":0.4262436959},
{"learn":[3.751365967],"iteration":440,"passed_time":0.3355985324,"remaining_time":0.4253958721},
{"learn":[3.747042875],"iteration":441,"passed_time":0.3361950907,"remaining_time":0.4244272864},
{"learn":[3.746190739],"iteration":442,"passed_time":0.3367797198,"remaining_time":0.4234453813},
{"learn":[3.741227216],"iteration":443,"passed_time":0.3373969481,"remaining_time":0.4225060882},
{"learn":[3.736235135],"iteration":444,"passed_time":0.3380157028,"remaining_time":0.4215701462},
{"learn":[3.732845363],"iteration":445,"passed_time":0.3386232391,"remaining_time":0.4206216916},
{"learn":[3.726665446],"iteration":446,"passed_time":0.3392599557,"remaining_time":0.4197108624},
{"learn":[3.723463057],"iteration":447,"passed_time":0.3398613619,"remaining_time":0.4187577495},
{"learn":[3.71897979],"iteration":448,"passed_time":0.3404680006,"remaining_time":0.4178126243},
{"learn":[3.717002101],"iteration":449,"passed_time":0.3411727061,"remaining_time":0.416988863},
{"learn":[3.713504011],"iteration":450,"passed_time":0.3420847843,"remaining_time":0.4164180634},
{"learn":[3.709104437],"iteration":451,"passed_time":0.3427539608,"remaining_time":0.4155512622},
{"learn":[3.704955884],"iteration":452,"passed_time":0.3434067415,"remaining_time":0.4146655356},
{"learn":[3.702456555],"iteration":453,"passed_time":0.344026586,"remaining_time":0.4137412246},
{"learn":[3.699095028],"iteration":454,"passed_time":0.3446485873,"remaining_time":0.4128208353},
{"learn":[3.696992552],"iteration":455,"passed_time":0.3453399605,"remaining_time":0.4119845143},
{"learn":[3.696731761],"iteration":456,"passed_time":0.3459381493,"remaining_time":0.4110381074},
{"learn":[3.693540843],"iteration":457,"passed_time":0.3465689664,"remaining_time":0.4101318337},
{"learn":[3.690421009],"iteration":458,"passed_time":0.3472011085,"remaining_time":0.4092283218},
{"learn":[3.686239974],"iteration":459,"passed_time":0.3478380947,"remaining_time":0.4083316764},
{"learn":[3.679655899],"iteration":460,"passed_time":0.348444316,"remaining_time":0.4074001872},
{"learn":[3.675607454],"iteration":461,"passed_time":0.3490513659,"remaining_time":0.4064710711},
{"learn":[3.673525915],"iteration":462,"passed_time":0.3496737194,"remaining_time":0.4055610958},
{"learn":[3.671683342],"iteration":463,"passed_time":0.3503203211,"remaining_time":0.404680371},
{"learn":[3.668715902],"iteration":464,"passed_time":0.3511233849,"remaining_time":0.4039806686},
{"learn":[3.666221679],"iteration":465,"passed_time":0.3517297892,"remaining_time":0.4030551661},
{"learn":[3.66506988],"iteration":466,"passed_time":0.3523445192,"remaining_time":0.4021405326},
{"learn":[3.66175184],"iteration":467,"passed_time":0.3529548019,"remaining_time":0.4012221252},
{"learn":[3.659506435],"iteration":468,"passed_time":0.3536156169,"remaining_time":0.4003622443},
{"learn":[3.655992178],"iteration":469,"passed_time":0.3542866123,"remaining_time":0.3995146905},
{"learn":[3.652440366],"iteration":470,"passed_time":0.3549363388,"remaining_time":0.3986439983},
{"learn":[3.649243568],"iteration":471,"passed_time":0.3562431957,"remaining_time":0.3985093375},
{"learn":[3.647368317],"iteration":472,"passed_time":0.3569200254,"remaining_time":0.3976677662},
{"learn":[3.646903644],"iteration":473,"passed_time":0.3575850467,"remaining_time":0.396813786},
{"learn":[3.644759384],"iteration":474,"passed_time":0.3582008888,"remaining_time":0.3959062455},
{"learn":[3.642026616],"iteration":475,"passed_time":0.3588992735,"remaining_time":0.3950907969},
{"learn":[3.638800027],"iteration":476,"passed_time":0.359615366,"remaining_time":0.3942952545},
{"learn":[3.635495163],"iteration":477,"passed_time":0.360393686,"remaining_time":0.3935680002},
{"learn":[3.633847376],"iteration":478,"passed_time":0.3611015794,"remaining_time":0.3927639309},
{"learn":[3.630605249],"iteration":479,"passed_time":0.3617314614,"remaining_time":0.3918757499},
{"learn":[3.627109376],"iteration":480,"passed_time":0.3623416361,"remaining_time":0.3909673787},
{"learn":[3.624392042],"iteration":481,"passed_time":0.3629901785,"remaining_time":0.3901014781},
{"learn":[3.621698867],"iteration":482,"passed_time":0.3636131493,"remaining_time":0.389209106},
{"learn":[3.621270396],"iteration":483,"passed_time":0.3642281934,"remaining_time":0.3883093962},
{"learn":[3.618967639],"iteration":484,"passed_time":0.3648322717,"remaining_time":0.3873992164},
{"learn":[3.61585091],"iteration":485,"passed_time":0.3655466999,"remaining_time":0.3866070036},
{"learn":[3.612347668],"iteration":486,"passed_time":0.3662452643,"remaining_time":0.3857983995},
{"learn":[3.606411937],"iteration":487,"passed_time":0.3668735671,"remaining_time":0.3849165294},
{"learn":[3.603283813],"iteration":488,"passed_time":0.3675336458,"remaining_time":0.3840689018},
{"learn":[3.600236743],"iteration":489,"passed_time":0.3681754462,"remaining_time":0.3832030154},
{"learn":[3.598213458],"iteration":490,"passed_time":0.3687916016,"remaining_time":0.3823114566},
{"learn":[3.597855396],"iteration":491,"passed_time":0.3693779891,"remaining_time":0.3813902814},
{"learn":[3.594907012],"iteration":492,"passed_time":0.3699995231,"remaining_time":0.380506609},
{"learn":[3.592319031],"iteration":493,"passed_time":0.370612481,"remaining_time":0.3796152133},
{"learn":[3.591219434],"iteration":494,"passed_time":0.3713256845,"remaining_time":0.3788272135},
{"learn":[3.58840227],"iteration":495,"passed_time":0.3720380552,"remaining_time":0.378038669},
{"learn":[3.583848186],"iteration":496,"passed_time":0.3726988511,"remaining_time":0.3771982337},
{"learn":[3.580885448],"iteration":497,"passed_time":0.3733250715,"remaining_time":0.3763236665},
{"learn":[3.57687757],"iteration":498,"passed_time":0.373955688,"remaining_time":0.3754545084},
{"learn":[3.573098816],"iteration":499,"passed_time":0.3745574703,"remaining_time":0.3745574703},
{"learn":[3.570969429],"iteration":500,"passed_time":0.375154953,"remaining_time":0.3736573284},
{"learn":[3.568953187],"iteration":501,"passed_time":0.3757752203,"remaining_time":0.3727809954},
{"learn":[3.565235126],"iteration":502,"passed_time":0.3764266385,"remaining_time":0.3719364599},
{"learn":[3.563075166],"iteration":503,"passed_time":0.3770358329,"remaining_time":0.3710511371},
{"learn":[3.55804937],"iteration":504,"passed_time":0.3776608233,"remaining_time":0.3701823911},
{"learn":[3.555149126],"iteration":505,"passed_time":0.3782747614,"remaining_time":0.3693038185},
{"learn":[3.549464077],"iteration":506,"passed_time":0.3788822341,"remaining_time":0.3684200028},
{"learn":[3.545425184],"iteration":507,"passed_time":0.379495571,"remaining_time":0.3675429546},
{"learn":[3.542153775],"iteration":508,"passed_time":0.3802614936,"remaining_time":0.3668141323},
{"learn":[3.537767035],"iteration":509,"passed_time":0.3810520767,"remaining_time":0.366108858},
{"learn":[3.533283831],"iteration":510,"passed_time":0.381699131,"remaining_time":0.3652659003},
{"learn":[3.531208045],"iteration":511,"passed_time":0.3823049027,"remaining_time":0.3643843604},
{"learn":[3.527310116],"iteration":512,"passed_time":0.3829609866,"remaining_time":0.3635516579},
{"learn":[3.525126708],"iteration":513,"passed_time":0.3836823291,"remaining_time":0.3627813462},
{"learn":[3.520321317],"iteration":514,"passed_time":0.3843854699,"remaining_time":0.3619940833},
{"learn":[3.515603919],"iteration":515,"passed_time":0.3849869864,"remaining_time":0.3611118245},
{"learn":[3.515203043],"iteration":516,"passed_time":0.3857236957,"remaining_time":0.3603569536},
{"learn":[3.514066006],"iteration":517,"passed_time":0.3864151865,"remaining_time":0.359560077},
{"learn":[3.506919849],"iteration":518,"passed_time":0.3872218299,"remaining_time":0.3588703279},
{"learn":[3.505123437],"iteration":519,"passed_time":0.388112792,"remaining_time":0.3582579618},
{"learn":[3.503381175],"iteration":520,"passed_time":0.3888803726,"remaining_time":0.3575310912},
{"learn":[3.501533137],"iteration":521,"passed_time":0.3895301236,"remaining_time":0.3566961668},
{"learn":[3.497204035],"iteration":522,"passed_time":0.3902906184,"remaining_time":0.3559629541},
{"learn":[3.496181772],"iteration":523,"passed_time":0.3909514867,"remaining_time":0.3551391368},
{"learn":[3.491825606],"iteration":524,"passed_time":0.3915913143,"remaining_time":0.3542969034},
{"learn":[3.486055808],"iteration":525,"passed_time":0.3922250341,"remaining_time":0.3534499356},
{"learn":[3.484553645],"iteration":526,"passed_time":0.3928120841,"remaining_time":0.3525618895},
{"learn":[3.479223819],"iteration":527,"passed_time":0.3934057244,"remaining_time":0.3516808749},
{"learn":[3.474977917],"iteration":528,"passed_time":0.3940141054,"remaining_time":0.3508140712},
{"learn":[3.472258785],"iteration":529,"passed_time":0.3946165655,"remaining_time":0.349942992},
{"learn":[3.469077991],"iteration":530,"passed_time":0.3952312657,"remaining_time":0.3490837356},
{"learn":[3.466224313],"iteration":531,"passed_time":0.3958718752,"remaining_time":0.348248191},
{"learn":[3.464323106],"iteration":532,"passed_time":0.3965954793,"remaining_time":0.3474860954},
{"learn":[3.462066117],"iteration":533,"passed_time":0.3972165714,"remaining_time":0.3466346859},
{"learn":[3.460513833],"iteration":534,"passed_time":0.3978551912,"remaining_time":0.3457993718},
{"learn":[3.456060369],"iteration":535,"passed_time":0.3984605723,"remaining_time":0.3449360178},
{"learn":[3.450952392],"iteration":536,"passed_time":0.3990579822,"remaining_time":0.3440667519},
{"learn":[3.449011448],"iteration":537,"passed_time":0.3996653339,"remaining_time":0.343207034},
{"learn":[3.446708103],"iteration":538,"passed_time":0.4004282198,"remaining_time":0.3424812789},
{"learn":[3.44428921],"iteration":539,"passed_time":0.4010616179,"remaining_time":0.3416450819},
{"learn":[3.440490899],"iteration":540,"passed_time":0.4016628419,"remaining_time":0.3407823372},
{"learn":[3.433728201],"iteration":541,"passed_time":0.4023230197,"remaining_time":0.3399703746},
{"learn":[3.42952735],"iteration":542,"passed_time":0.4030902297,"remaining_time":0.3392490515},
{"learn":[3.426378573],"iteration":543,"passed_time":0.4037992099,"remaining_time":0.3384787495},
{"learn":[3.423004346],"iteration":544,"passed_time":0.4045343606,"remaining_time":0.3377305212},
{"learn":[3.420708205],"iteration":545,"passed_time":0.4052063612,"remaining_time":0.3369298314},
{"learn":[3.418750128],"iteration":546,"passed_time":0.4058996793,"remaining_time":0.3361472664},
{"learn":[3.417209249],"iteration":547,"passed_time":0.4065334657,"remaining_time":0.3353159243},
{"learn":[3.413695019],"iteration":548,"passed_time":0.40712199,"remaining_time":0.3344481193},
{"learn":[3.410095068],"iteration":549,"passed_time":0.407723466,"remaining_time":0.3335919267},
{"learn":[3.407513816],"iteration":550,"passed_time":0.4083850818,"remaining_time":0.3327856655},
{"learn":[3.405361876],"iteration":551,"passed_time":0.4090018084,"remaining_time":0.3319434967},
{"learn":[3.401155074],"iteration":552,"passed_time":0.4096257144,"remaining_time":0.3311079463},
{"learn":[3.398315707],"iteration":553,"passed_time":0.4102325146,"remaining_time":0.330259389},
{"learn":[3.396858499],"iteration":554,"passed_time":0.4109955261,"remaining_time":0.3295369533},
{"learn":[3.396475672],"iteration":555,"passed_time":0.4116912529,"remaining_time":0.3287606408},
{"learn":[3.394289568],"iteration":556,"passed_time":0.4123000475,"remaining_time":0.3279154776},
{"learn":[3.392261432],"iteration":557,"passed_time":0.4129014851,"remaining_time":0.3270653341},
{"learn":[3.387340766],"iteration":558,"passed_time":0.4135984458,"remaining_time":0.3262914393},
{"learn":[3.383342954],"iteration":559,"passed_time":0.4142914721,"remaining_time":0.3255147281},
{"learn":[3.379769242],"iteration":560,"passed_time":0.4150036199,"remaining_time":0.3247532784},
{"learn":[3.376525106],"iteration":561,"passed_time":0.4156384112,"remaining_time":0.3239317155},
{"learn":[3.37429355],"iteration":562,"passed_time":0.4162679899,"remaining_time":0.3231067701},
{"learn":[3.371075954],"iteration":563,"passed_time":0.4169013061,"remaining_time":0.3222854068},
{"learn":[3.364795948],"iteration":564,"passed_time":0.4175890782,"remaining_time":0.3215066354},
{"learn":[3.360016601],"iteration":565,"passed_time":0.4183425439,"remaining_time":0.3207785584},
{"learn":[3.358336009],"iteration":566,"passed_time":0.4190001737,"remaining_time":0.3199772049},
{"learn":[3.355907213],"iteration":567,"passed_time":0.4196685276,"remaining_time":0.3191845139},
{"learn":[3.351701067],"iteration":568,"passed_time":0.4204180938,"remaining_time":0.3184537758},
{"learn":[3.348835236],"iteration":569,"passed_time":0.421234553,"remaining_time":0.3177734347},
{"learn":[3.343414418],"iteration":570,"passed_time":0.4219580855,"remaining_time":0.3170227998},
{"learn":[3.338190323],"iteration":571,"passed_time":0.4226110994,"remaining_time":0.316219494},
{"learn":[3.335805786],"iteration":572,"passed_time":0.4232946393,"remaining_time":0.3154394607},
{"learn":[3.332092713],"iteration":573,"passed_time":0.4239968871,"remaining_time":0.314673648},
{"learn":[3.327934078],"iteration":574,"passed_time":0.4247756479,"remaining_time":0.3139646094},
{"learn":[3.325963811],"iteration":575,"passed_time":0.425471433,"remaining_time":0.3131942493},
{"learn":[3.324499771],"iteration":576,"passed_time":0.4261363868,"remaining_time":0.3124015453},
{"learn":[3.32286592],"iteration":577,"passed_time":0.4267694089,"remaining_time":0.3115859698},
{"learn":[3.320319738],"iteration":578,"passed_time":0.4273875593,"remaining_time":0.3107602115},
{"learn":[3.317579867],"iteration":579,"passed_time":0.4280678382,"remaining_time":0.3099801587},
{"learn":[3.31284327],"iteration":580,"passed_time":0.4287743553,"remaining_time":0.3092193716},
{"learn":[3.310040449],"iteration":581,"passed_time":0.4297233113,"remaining_time":0.3086328937},
{"learn":[3.308033258],"iteration":582,"passed_time":0.4304944487,"remaining_time":0.3079179847},
{"learn":[3.307171961],"iteration":583,"passed_time":0.4311539315,"remaining_time":0.3071233485},
{"learn":[3.302737717],"iteration":584,"passed_time":0.4317700011,"remaining_time":0.3062983768},
{"learn":[3.301443412],"iteration":585,"passed_time":0.4324958442,"remaining_time":0.3055516715},
{"learn":[3.300050528],"iteration":586,"passed_time":0.4334217655,"remaining_time":0.3049458078},
{"learn":[3.298261033],"iteration":587,"passed_time":0.4343181515,"remaining_time":0.3043181606},
{"learn":[3.294741511],"iteration":588,"passed_time":0.4351289525,"remaining_time":0.3036298802},
{"learn":[3.291592626],"iteration":589,"passed_time":0.4358696285,"remaining_time":0.3028924537},
{"learn":[3.288569165],"iteration":590,"passed_time":0.4364915577,"remaining_time":0.3020728378},
{"learn":[3.287100177],"iteration":591,"passed_time":0.4371328072,"remaining_time":0.3012672049},
{"learn":[3.2846438],"iteration":592,"passed_time":0.4377677493,"remaining_time":0.3004577976},
{"learn":[3.281195527],"iteration":593,"passed_time":0.4384048036,"remaining_time":0.2996504213},
{"learn":[3.277815944],"iteration":594,"passed_time":0.4390492054,"remaining_time":0.2988486188},
{"learn":[3.276279107],"iteration":595,"passed_time":0.4397983408,"remaining_time":0.2981183384},
{"learn":[3.274448679],"iteration":596,"passed_time":0.4404474645,"remaining_time":0.2973204828},
{"learn":[3.271771598],"iteration":597,"passed_time":0.4410891478,"remaining_time":0.2965181228},
{"learn":[3.270369417],"iteration":598,"passed_time":0.442898013,"remaining_time":0.2964976682},
{"learn":[3.26960924],"iteration":599,"passed_time":0.4438434507,"remaining_time":0.2958956338},
{"learn":[3.266317157],"iteration":600,"passed_time":0.4447103967,"remaining_time":0.2952403465},
{"learn":[3.264031387],"iteration":601,"passed_time":0.4453552369,"remaining_time":0.2944375154},
{"learn":[3.262648979],"iteration":602,"passed_time":0.4459748516,"remaining_time":0.2936186005},
{"learn":[3.259203764],"iteration":603,"passed_time":0.4465925418,"remaining_time":0.2927990837},
{"learn":[3.256952427],"iteration":604,"passed_time":0.4472632561,"remaining_time":0.2920148531},
{"learn":[3.254066962],"iteration":605,"passed_time":0.4481505072,"remaining_time":0.2913717819},
{"learn":[3.252215054],"iteration":606,"passed_time":0.4489003691,"remaining_time":0.290638954},
{"learn":[3.249789624],"iteration":607,"passed_time":0.4496048996,"remaining_time":0.2898768431},
{"learn":[3.248433107],"iteration":608,"passed_time":0.4502974833,"remaining_time":0.2891072512},
{"learn":[3.246486028],"iteration":609,"passed_time":0.4510301606,"remaining_time":0.2883635453},
{"learn":[3.244353431],"iteration":610,"passed_time":0.4517641292,"remaining_time":0.2876206976},
{"learn":[3.240005086],"iteration":611,"passed_time":0.4523812441,"remaining_time":0.2868037953},
{"learn":[3.235314661],"iteration":612,"passed_time":0.4530066849,"remaining_time":0.285992801},
{"learn":[3.232240981],"iteration":613,"passed_time":0.4536305004,"remaining_time":0.2851813895},
{"learn":[3.230254239],"iteration":614,"passed_time":0.4542465171,"remaining_time":0.2843657059},
{"learn":[3.227912969],"iteration":615,"passed_time":0.454883308,"remaining_time":0.2835636206},
{"learn":[3.226075276],"iteration":616,"passed_time":0.4555157641,"remaining_time":0.2827593803},
{"learn":[3.224368195],"iteration":617,"passed_time":0.4564183123,"remaining_time":0.2821226461},
{"learn":[3.22312953],"iteration":618,"passed_time":0.4572271894,"remaining_time":0.2814273977},
{"learn":[3.219435627],"iteration":619,"passed_time":0.4579828952,"remaining_time":0.2806991939},
{"learn":[3.218568319],"iteration":620,"passed_time":0.4590504645,"remaining_time":0.2801612335},
{"learn":[3.212870385],"iteration":621,"passed_time":0.460170259,"remaining_time":0.2796533085},
{"learn":[3.211224098],"iteration":622,"passed_time":0.4609016807,"remaining_time":0.2789084007},
{"learn":[3.209435989],"iteration":623,"passed_time":0.4615277403,"remaining_time":0.2781000486},
{"learn":[3.207777909],"iteration":624,"passed_time":0.4621779584,"remaining_time":0.277306775},
{"learn":[3.205193687],"iteration":625,"passed_time":0.4630992022,"remaining_time":0.2766758812},
{"learn":[3.202434057],"iteration":626,"passed_time":0.4642274275,"remaining_time":0.2761671937},
{"learn":[3.198733192],"iteration":627,"passed_time":0.4652014496,"remaining_time":0.2755651899},
{"learn":[3.193680917],"iteration":628,"passed_time":0.4658825797,"remaining_time":0.2747892481},
{"learn":[3.189643353],"iteration":629,"passed_time":0.4665659003,"remaining_time":0.2740148938},
{"learn":[3.18687006],"iteration":630,"passed_time":0.4671817408,"remaining_time":0.2732013667},
{"learn":[3.184040327],"iteration":631,"passed_time":0.4678146059,"remaining_time":0.2723983781},
{"learn":[3.182113843],"iteration":632,"passed_time":0.4684514435,"remaining_time":0.2715982303},
{"learn":[3.180322358],"iteration":633,"passed_time":0.4691004416,"remaining_time":0.2708056177},
{"learn":[3.17788477],"iteration":634,"passed_time":0.4697055309,"remaining_time":0.2699882186},
{"learn":[3.176122503],"iteration":635,"passed_time":0.4703143737,"remaining_time":0.2691736353},
{"learn":[3.174587156],"iteration":636,"passed_time":0.4709791453,"remaining_time":0.2683915694},
{"learn":[3.171867242],"iteration":637,"passed_time":0.4717644343,"remaining_time":0.2676782527},
{"learn":[3.168084636],"iteration":638,"passed_time":0.4725018118,"remaining_time":0.2669376433},
{"learn":[3.16529821],"iteration":639,"passed_time":0.4731135749,"remaining_time":0.2661263859},
{"learn":[3.162594087],"iteration":640,"passed_time":0.4737515177,"remaining_time":0.2653304132},
{"learn":[3.159385717],"iteration":641,"passed_time":0.4743864092,"remaining_time":0.2645332313},
{"learn":[3.158018419],"iteration":642,"passed_time":0.4749756933,"remaining_time":0.2637112325},
{"learn":[3.152820182],"iteration":643,"passed_time":0.4755705904,"remaining_time":0.2628930593},
{"learn":[3.151554583],"iteration":644,"passed_time":0.4761533615,"remaining_time":0.2620689044},
{"learn":[3.149887288],"iteration":645,"passed_time":0.4767500845,"remaining_time":0.2612531423},
{"learn":[3.148545511],"iteration":646,"passed_time":0.4773905948,"remaining_time":0.2604619474},
{"learn":[3.146767914],"iteration":647,"passed_time":0.4781990529,"remaining_time":0.2597624485},
{"learn":[3.145486329],"iteration":648,"passed_time":0.4791210067,"remaining_time":0.2591239959},
{"learn":[3.142804834],"iteration":649,"passed_time":0.4797688721,"remaining_time":0.258337085},
{"learn":[3.142055337],"iteration":650,"passed_time":0.480368899,"remaining_time":0.2575249551},
{"learn":[3.140208978],"iteration":651,"passed_time":0.4809625906,"remaining_time":0.2567100944},
{"learn":[3.137285836],"iteration":652,"passed_time":0.4815681364,"remaining_time":0.2559022103},
{"learn":[3.135047027],"iteration":653,"passed_time":0.4821818394,"remaining_time":0.2550992606},
{"learn":[3.133076945],"iteration":654,"passed_time":0.4828012436,"remaining_time":0.2542998917},
{"learn":[3.131107603],"iteration":655,"passed_time":0.4834223005,"remaining_time":0.2535019381},
{"learn":[3.127769077],"iteration":656,"passed_time":0.4840390394,"remaining_time":0.2527022687},
{"learn":[3.125455511],"iteration":657,"passed_time":0.4846438277,"remaining_time":0.2518969439},
{"learn":[3.12414053],"iteration":658,"passed_time":0.4852463337,"remaining_time":0.2510910467},
{"learn":[3.120304443],"iteration":659,"passed_time":0.4858597741,"remaining_time":0.2502913988},
{"learn":[3.117930015],"iteration":660,"passed_time":0.4865038315,"remaining_time":0.2495080165},
{"learn":[3.111982238],"iteration":661,"passed_time":0.487240586,"remaining_time":0.2487723838},
{"learn":[3.109702372],"iteration":662,"passed_time":0.487868852,"remaining_time":0.2479816035},
{"learn":[3.109173568],"iteration":663,"passed_time":0.4884710264,"remaining_time":0.2471781097},
{"learn":[3.107633276],"iteration":664,"passed_time":0.4890862206,"remaining_time":0.2463817803},
{"learn":[3.107162082],"iteration":665,"passed_time":0.4896870294,"remaining_time":0.2455787805},
{"learn":[3.106287472],"iteration":666,"passed_time":0.4902739201,"remaining_time":0.2447694384},
{"learn":[3.102120333],"iteration":667,"passed_time":0.4909240908,"remaining_time":0.2439922128},
{"learn":[3.100437642],"iteration":668,"passed_time":0.4915503303,"remaining_time":0.2432035267},
{"learn":[3.098912499],"iteration":669,"passed_time":0.4921550681,"remaining_time":0.242404735},
{"learn":[3.098515341],"iteration":670,"passed_time":0.4927786975,"remaining_time":0.2416157846},
{"learn":[3.096478095],"iteration":671,"passed_time":0.4936035525,"remaining_time":0.2409255435},
{"learn":[3.095365785],"iteration":672,"passed_time":0.4944069027,"remaining_time":0.2402244535},
{"learn":[3.094224321],"iteration":673,"passed_time":0.495156837,"remaining_time":0.2394972238},
{"learn":[3.093548241],"iteration":674,"passed_time":0.4957766601,"remaining_time":0.2387072808},
{"learn":[3.093105637],"iteration":675,"passed_time":0.496417396,"remaining_time":0.2379278643},
{"learn":[3.092130943],"iteration":676,"passed_time":0.497052119,"remaining_time":0.2371459888},
{"learn":[3.091702099],"iteration":677,"passed_time":0.4976386184,"remaining_time":0.2363416447},
{"learn":[3.089476187],"iteration":678,"passed_time":0.4983855612,"remaining_time":0.2356137925},
{"learn":[3.083920344],"iteration":679,"passed_time":0.4990960551,"remaining_time":0.2348687318},
{"learn":[3.081205392],"iteration":680,"passed_time":0.4997338749,"remaining_time":0.23408973},
{"learn":[3.077706914],"iteration":681,"passed_time":0.5004117482,"remaining_time":0.2333298181},
{"learn":[3.075338555],"iteration":682,"passed_time":0.5010255669,"remaining_time":0.2325404168},
{"learn":[3.070220552],"iteration":683,"passed_time":0.5016513346,"remaining_time":0.2317570493},
{"learn":[3.068784651],"iteration":684,"passed_time":0.5023964899,"remaining_time":0.2310290428},
{"learn":[3.067283463],"iteration":685,"passed_time":0.5030827195,"remaining_time":0.2302740145},
{"learn":[3.0654487],"iteration":686,"passed_time":0.5036949812,"remaining_time":0.2294854863},
{"learn":[3.062865582],"iteration":687,"passed_time":0.5043173937,"remaining_time":0.2287020739},
{"learn":[3.058515795],"iteration":688,"passed_time":0.5049126646,"remaining_time":0.2279068776},
{"learn":[3.057248933],"iteration":689,"passed_time":0.5055315724,"remaining_time":0.2271228804},
{"learn":[3.055842872],"iteration":690,"passed_time":0.5061461501,"remaining_time":0.2263374246},
{"learn":[3.054964819],"iteration":691,"passed_time":0.5067983238,"remaining_time":0.2255691962},
{"learn":[3.053114841],"iteration":692,"passed_time":0.5074213996,"remaining_time":0.2247884122},
{"learn":[3.051054972],"iteration":693,"passed_time":0.5081648446,"remaining_time":0.2240611563},
{"learn":[3.049803837],"iteration":694,"passed_time":0.5088788593,"remaining_time":0.2233209382},
{"learn":[3.047643065],"iteration":695,"passed_time":0.5096951687,"remaining_time":0.222625476},
{"learn":[3.045686393],"iteration":696,"passed_time":0.5103661139,"remaining_time":0.2218664742},
{"learn":[3.041823677],"iteration":697,"passed_time":0.5110189061,"remaining_time":0.2210998706},
{"learn":[3.037132043],"iteration":698,"passed_time":0.5116452081,"remaining_time":0.2203221855},
{"learn":[3.034079493],"iteration":699,"passed_time":0.5125120767,"remaining_time":0.2196480329},
{"learn":[3.031819774],"iteration":700,"passed_time":0.5135959907,"remaining_time":0.2190659076},
{"learn":[3.028852293],"iteration":701,"passed_time":0.5142424431,"remaining_time":0.2182966496},
{"learn":[3.026125506],"iteration":702,"passed_time":0.5149447905,"remaining_time":0.2175513553},
{"learn":[3.023867845],"iteration":703,"passed_time":0.5156059245,"remaining_time":0.2167888546},
{"learn":[3.01753719],"iteration":704,"passed_time":0.5162820413,"remaining_time":0.2160329109},
{"learn":[3.015105282],"iteration":705,"passed_time":0.5169505437,"remaining_time":0.2152740225},
{"learn":[3.013280173],"iteration":706,"passed_time":0.5176784355,"remaining_time":0.2145400023},
{"learn":[3.011333657],"iteration":707,"passed_time":0.5183060169,"remaining_time":0.2137646284},
{"learn":[3.008110771],"iteration":708,"passed_time":0.5189968253,"remaining_time":0.2130156222},
{"learn":[3.005055823],"iteration":709,"passed_time":0.5197193897,"remaining_time":0.2122797507},
{"learn":[3.003872652],"iteration":710,"passed_time":0.520344282,"remaining_time":0.2115042159},
{"learn":[3.001837416],"iteration":711,"passed_time":0.5209923596,"remaining_time":0.2107384825},
{"learn":[3.000150746],"iteration":712,"passed_time":0.522326638,"remaining_time":0.2102492919},
{"learn":[2.995970201],"iteration":713,"passed_time":0.5235349123,"remaining_time":0.2097072618},
{"learn":[2.993899406],"iteration":714,"passed_time":0.5250047185,"remaining_time":0.2092676151},
{"learn":[2.992555745],"iteration":715,"passed_time":0.5260997396,"remaining_time":0.208676433},
{"learn":[2.990209635],"iteration":716,"passed_time":0.5269691781,"remaining_time":0.2079948081},
{"learn":[2.989617243],"iteration":717,"passed_time":0.5284454594,"remaining_time":0.2075510022},
{"learn":[2.987664472],"iteration":718,"passed_time":0.5293074958,"remaining_time":0.2068642647},
{"learn":[2.986089643],"iteration":719,"passed_time":0.530281081,"remaining_time":0.2062204204},
{"learn":[2.981857018],"iteration":720,"passed_time":0.5309396073,"remaining_time":0.2054537454},
{"learn":[2.980614646],"iteration":721,"passed_time":0.531657146,"remaining_time":0.2047100922},
{"learn":[2.975368557],"iteration":722,"passed_time":0.5324022461,"remaining_time":0.2039770708},
{"learn":[2.972582031],"iteration":723,"passed_time":0.5331041508,"remaining_time":0.2032275492},
{"learn":[2.970002666],"iteration":724,"passed_time":0.5337083441,"remaining_time":0.202441096},
{"learn":[2.968683446],"iteration":725,"passed_time":0.5343880558,"remaining_time":0.2016836464},
{"learn":[2.96448452],"iteration":726,"passed_time":0.5350025768,"remaining_time":0.2009019305},
{"learn":[2.962883366],"iteration":727,"passed_time":0.5356342326,"remaining_time":0.2001270759},
{"learn":[2.959326935],"iteration":728,"passed_time":0.5362535448,"remaining_time":0.1993480256},
{"learn":[2.958232148],"iteration":729,"passed_time":0.5368725898,"remaining_time":0.198569314},
{"learn":[2.957555486],"iteration":730,"passed_time":0.5375622302,"remaining_time":0.1978170177},
{"learn":[2.956866448],"iteration":731,"passed_time":0.5389626526,"remaining_time":0.1973251242},
{"learn":[2.954108954],"iteration":732,"passed_time":0.539896704,"remaining_time":0.1966608731},
{"learn":[2.952491087],"iteration":733,"passed_time":0.5406340489,"remaining_time":0.1959246008},
{"learn":[2.951698628],"iteration":734,"passed_time":0.5417601895,"remaining_time":0.1953285037},
{"learn":[2.948079006],"iteration":735,"passed_time":0.5425558844,"remaining_time":0.1946124368},
{"learn":[2.946331629],"iteration":736,"passed_time":0.5432765365,"remaining_time":0.1938693746},
{"learn":[2.944144948],"iteration":737,"passed_time":0.5439372271,"remaining_time":0.193105086},
{"learn":[2.940617798],"iteration":738,"passed_time":0.544600033,"remaining_time":0.1923418249},
{"learn":[2.939266665],"iteration":739,"passed_time":0.5452357203,"remaining_time":0.1915693071},
{"learn":[2.93650572],"iteration":740,"passed_time":0.546155203,"remaining_time":0.190896353},
{"learn":[2.934164704],"iteration":741,"passed_time":0.5468002891,"remaining_time":0.1901273242},
{"learn":[2.931074362],"iteration":742,"passed_time":0.5476451321,"remaining_time":0.189427724},
{"learn":[2.928634183],"iteration":743,"passed_time":0.5483697061,"remaining_time":0.1886863505},
{"learn":[2.927040008],"iteration":744,"passed_time":0.5491122869,"remaining_time":0.1879511854},
{"learn":[2.926092611],"iteration":745,"passed_time":0.5497784987,"remaining_time":0.1871899982},
{"learn":[2.923630445],"iteration":746,"passed_time":0.5504832359,"remaining_time":0.1864421134},
{"learn":[2.922389566],"iteration":747,"passed_time":0.551111407,"remaining_time":0.1856685489},
{"learn":[2.918868362],"iteration":748,"passed_time":0.5517183214,"remaining_time":0.1848882492},
{"learn":[2.917118663],"iteration":749,"passed_time":0.5523915221,"remaining_time":0.1841305074},
{"learn":[2.916101371],"iteration":750,"passed_time":0.5533104782,"remaining_time":0.1834544728},
{"learn":[2.912017771],"iteration":751,"passed_time":0.5542735661,"remaining_time":0.1827923463},
{"learn":[2.909396452],"iteration":752,"passed_time":0.5550301588,"remaining_time":0.1820616856},
{"learn":[2.906334922],"iteration":753,"passed_time":0.5557294017,"remaining_time":0.1813122451},
{"learn":[2.903814496],"iteration":754,"passed_time":0.5564233391,"remaining_time":0.180561216},
{"learn":[2.901186577],"iteration":755,"passed_time":0.5571746634,"remaining_time":0.1798288596},
{"learn":[2.898703868],"iteration":756,"passed_time":0.5580663263,"remaining_time":0.1791415024},
{"learn":[2.896608722],"iteration":757,"passed_time":0.5587980179,"remaining_time":0.1784025334},
{"learn":[2.892714453],"iteration":758,"passed_time":0.5594520133,"remaining_time":0.1776389133},
{"learn":[2.890793313],"iteration":759,"passed_time":0.5601556029,"remaining_time":0.176891243},
{"learn":[2.888300939],"iteration":760,"passed_time":0.5607969293,"remaining_time":0.1761241342},
{"learn":[2.88560674],"iteration":761,"passed_time":0.5614882352,"remaining_time":0.1753729658},
{"learn":[2.884480773],"iteration":762,"passed_time":0.5622486017,"remaining_time":0.1746434058},
{"learn":[2.881716817],"iteration":763,"passed_time":0.5629052577,"remaining_time":0.1738817288},
{"learn":[2.87990176],"iteration":764,"passed_time":0.5635750442,"remaining_time":0.17312436},
{"learn":[2.878302699],"iteration":765,"passed_time":0.5643273481,"remaining_time":0.1723924275},
{"learn":[2.876326347],"iteration":766,"passed_time":0.5649816257,"remaining_time":0.1716306633},
{"learn":[2.87384679],"iteration":767,"passed_time":0.5656629082,"remaining_time":0.1708773369},
{"learn":[2.871460903],"iteration":768,"passed_time":0.5663229444,"remaining_time":0.1701178155},
{"learn":[2.869993153],"iteration":769,"passed_time":0.566955206,"remaining_time":0.1693502563},
{"learn":[2.869058594],"iteration":770,"passed_time":0.567853767,"remaining_time":0.1686621435},
{"learn":[2.868264232],"iteration":771,"passed_time":0.5689396018,"remaining_time":0.1680287943},
{"learn":[2.86751496],"iteration":772,"passed_time":0.5699488352,"remaining_time":0.1673717795},
{"learn":[2.866368263],"iteration":773,"passed_time":0.5706885822,"remaining_time":0.1666351674},
{"learn":[2.865330949],"iteration":774,"passed_time":0.571506348,"remaining_time":0.1659211978},
{"learn":[2.863463721],"iteration":775,"passed_time":0.5722754875,"remaining_time":0.1651929242},
{"learn":[2.862260531],"iteration":776,"passed_time":0.5729588494,"remaining_time":0.1644399272},
{"learn":[2.859534469],"iteration":777,"passed_time":0.5737454485,"remaining_time":0.1637165676},
{"learn":[2.858477639],"iteration":778,"passed_time":0.5744064382,"remaining_time":0.1629574106},
{"learn":[2.855344829],"iteration":779,"passed_time":0.5750511647,"remaining_time":0.1621939182},
{"learn":[2.854780385],"iteration":780,"passed_time":0.575706166,"remaining_time":0.1614336112},
{"learn":[2.852387043],"iteration":781,"passed_time":0.5764563193,"remaining_time":0.1607000992},
{"learn":[2.850390808],"iteration":782,"passed_time":0.5772245238,"remaining_time":0.1599715475},
{"learn":[2.846581431],"iteration":783,"passed_time":0.5778636084,"remaining_time":0.1592073207},
{"learn":[2.845593141],"iteration":784,"passed_time":0.5784720637,"remaining_time":0.1584350238},
{"learn":[2.843955956],"iteration":785,"passed_time":0.579112514,"remaining_time":0.1576718549},
{"learn":[2.842079851],"iteration":786,"passed_time":0.579889599,"remaining_time":0.1569459779},
{"learn":[2.837824296],"iteration":787,"passed_time":0.5806535747,"remaining_time":0.156216444},
{"learn":[2.83569478],"iteration":788,"passed_time":0.581326499,"remaining_time":0.1554624731},
{"learn":[2.833528673],"iteration":789,"passed_time":0.5820419596,"remaining_time":0.1547200146},
{"learn":[2.832140983],"iteration":790,"passed_time":0.5829021617,"remaining_time":0.1540158683},
{"learn":[2.830969969],"iteration":791,"passed_time":0.5840948494,"remaining_time":0.1533986473},
{"learn":[2.829969918],"iteration":792,"passed_time":0.5849422244,"remaining_time":0.1526898366},
{"learn":[2.828167408],"iteration":793,"passed_time":0.5857216553,"remaining_time":0.1519630491},
{"learn":[2.826118742],"iteration":794,"passed_time":0.5864031018,"remaining_time":0.1512108627},
{"learn":[2.824912004],"iteration":795,"passed_time":0.5870020993,"remaining_time":0.1504377239},
{"learn":[2.824395896],"iteration":796,"passed_time":0.5876763581,"remaining_time":0.1496841916},
{"learn":[2.820424182],"iteration":797,"passed_time":0.5882903238,"remaining_time":0.1489155957},
{"learn":[2.818757056],"iteration":798,"passed_time":0.5888926131,"remaining_time":0.1481444496},
{"learn":[2.816956089],"iteration":799,"passed_time":0.5895138346,"remaining_time":0.1473784587},
{"learn":[2.814521366],"iteration":800,"passed_time":0.5901355318,"remaining_time":0.1466129474},
{"learn":[2.813215585],"iteration":801,"passed_time":0.5908079222,"remaining_time":0.14586031},
{"learn":[2.809831117],"iteration":802,"passed_time":0.591575149,"remaining_time":0.1451311387},
{"learn":[2.808138146],"iteration":803,"passed_time":0.592282681,"remaining_time":0.1443873202},
{"learn":[2.805301693],"iteration":804,"passed_time":0.5929085881,"remaining_time":0.1436238195},
{"learn":[2.803324616],"iteration":805,"passed_time":0.5935230386,"remaining_time":0.1428579026},
{"learn":[2.802412863],"iteration":806,"passed_time":0.5941454603,"remaining_time":0.1420942675},
{"learn":[2.800842721],"iteration":807,"passed_time":0.5947431123,"remaining_time":0.141325096},
{"learn":[2.800160271],"iteration":808,"passed_time":0.5953603957,"remaining_time":0.1405609834},
{"learn":[2.79876606],"iteration":809,"passed_time":0.5959812481,"remaining_time":0.1397980705},
{"learn":[2.796538034],"iteration":810,"passed_time":0.5966044763,"remaining_time":0.1390360617},
{"learn":[2.793825807],"iteration":811,"passed_time":0.5972898535,"remaining_time":0.1382887838},
{"learn":[2.791722007],"iteration":812,"passed_time":0.5980543408,"remaining_time":0.1375598545},
{"learn":[2.788555677],"iteration":813,"passed_time":0.5987986639,"remaining_time":0.1368262303},
{"learn":[2.785901094],"iteration":814,"passed_time":0.5994383437,"remaining_time":0.1360688265},
{"learn":[2.783949061],"iteration":815,"passed_time":0.6000338995,"remaining_time":0.1353017616},
{"learn":[2.781764951],"iteration":816,"passed_time":0.6006681615,"remaining_time":0.1345437865},
{"learn":[2.780558893],"iteration":817,"passed_time":0.6012925821,"remaining_time":0.1337839241},
{"learn":[2.777270687],"iteration":818,"passed_time":0.6018828327,"remaining_time":0.1330168409},
{"learn":[2.773625163],"iteration":819,"passed_time":0.6024927416,"remaining_time":0.1322545042},
{"learn":[2.773408216],"iteration":820,"passed_time":0.6031179372,"remaining_time":0.1314958718},
{"learn":[2.772008804],"iteration":821,"passed_time":0.6037188625,"remaining_time":0.1307323084},
{"learn":[2.768336928],"iteration":822,"passed_time":0.6043287109,"remaining_time":0.1299710593},
{"learn":[2.766250848],"iteration":823,"passed_time":0.604921662,"remaining_time":0.1292065686},
{"learn":[2.764530146],"iteration":824,"passed_time":0.6055534881,"remaining_time":0.1284507399},
{"learn":[2.763888087],"iteration":825,"passed_time":0.6061874913,"remaining_time":0.1276956701},
{"learn":[2.762850672],"iteration":826,"passed_time":0.6068271864,"remaining_time":0.1269420837},
{"learn":[2.761700256],"iteration":827,"passed_time":0.6074470002,"remaining_time":0.1261846426},
{"learn":[2.759721054],"iteration":828,"passed_time":0.6080393914,"remaining_time":0.1254218769},
{"learn":[2.757306722],"iteration":829,"passed_time":0.6086435188,"remaining_time":0.1246619255},
{"learn":[2.753995546],"iteration":830,"passed_time":0.6092424789,"remaining_time":0.1239012983},
{"learn":[2.75353515],"iteration":831,"passed_time":0.6098535427,"remaining_time":0.1231435038},
{"learn":[2.751159591],"iteration":832,"passed_time":0.6104355051,"remaining_time":0.1223802273},
{"learn":[2.750312767],"iteration":833,"passed_time":0.6110570245,"remaining_time":0.1216252591},
{"learn":[2.749632238],"iteration":834,"passed_time":0.6116470729,"remaining_time":0.1208643917},
{"learn":[2.748933159],"iteration":835,"passed_time":0.6123603343,"remaining_time":0.1201281039},
{"learn":[2.746785743],"iteration":836,"passed_time":0.6131263564,"remaining_time":0.1194021459},
{"learn":[2.746117333],"iteration":837,"passed_time":0.6137809821,"remaining_time":0.1186545574},
{"learn":[2.744141176],"iteration":838,"passed_time":0.6143950704,"remaining_time":0.1178994116},
{"learn":[2.74178309],"iteration":839,"passed_time":0.6150093156,"remaining_time":0.1171446316},
{"learn":[2.740277569],"iteration":840,"passed_time":0.6156177127,"remaining_time":0.1163890801},
{"learn":[2.739212313],"iteration":841,"passed_time":0.616252347,"remaining_time":0.1156388014},
{"learn":[2.738003106],"iteration":842,"passed_time":0.616866665,"remaining_time":0.1148850135},
{"learn":[2.735501011],"iteration":843,"passed_time":0.6174757797,"remaining_time":0.1141305943},
{"learn":[2.73366256],"iteration":844,"passed_time":0.6180690976,"remaining_time":0.1133736214},
{"learn":[2.733077055],"iteration":845,"passed_time":0.6186764071,"remaining_time":0.1126195824},
{"learn":[2.731085141],"iteration":846,"passed_time":0.6192807865,"remaining_time":0.1118653605},
{"learn":[2.727500986],"iteration":847,"passed_time":0.6198817202,"remaining_time":0.1111108744},
{"learn":[2.723593188],"iteration":848,"passed_time":0.6204913656,"remaining_time":0.1103582994},
{"learn":[2.723192185],"iteration":849,"passed_time":0.621158478,"remaining_time":0.109616202},
{"learn":[2.722441081],"iteration":850,"passed_time":0.6217926436,"remaining_time":0.1088685122},
{"learn":[2.72112219],"iteration":851,"passed_time":0.6224128725,"remaining_time":0.108118668},
{"learn":[2.718880309],"iteration":852,"passed_time":0.6230249535,"remaining_time":0.1073677235},
{"learn":[2.717245895],"iteration":853,"passed_time":0.6236214535,"remaining_time":0.1066144405},
{"learn":[2.71560929],"iteration":854,"passed_time":0.624245142,"remaining_time":0.1058661352},
{"learn":[2.714695811],"iteration":855,"passed_time":0.6248604326,"remaining_time":0.1051167083},
{"learn":[2.713355224],"iteration":856,"passed_time":0.6254538141,"remaining_time":0.1043639386},
{"learn":[2.712206343],"iteration":857,"passed_time":0.6260658988,"remaining_time":0.1036146359},
{"learn":[2.708587057],"iteration":858,"passed_time":0.6271131855,"remaining_time":0.1029370887},
{"learn":[2.706004743],"iteration":859,"passed_time":0.6284841928,"remaining_time":0.1023113802},
{"learn":[2.704677648],"iteration":860,"passed_time":0.6292114527,"remaining_time":0.1015800139},
{"learn":[2.702196925],"iteration":861,"passed_time":0.6298639256,"remaining_time":0.1008366841},
{"learn":[2.701486975],"iteration":862,"passed_time":0.6305208665,"remaining_time":0.1000942743},
{"learn":[2.69879114],"iteration":863,"passed_time":0.6311673311,"remaining_time":0.09935041323},
{"learn":[2.696118417],"iteration":864,"passed_time":0.6317968126,"remaining_time":0.09860412682},
{"learn":[2.692565913],"iteration":865,"passed_time":0.6324299771,"remaining_time":0.09785868006},
{"learn":[2.691648584],"iteration":866,"passed_time":0.6330463752,"remaining_time":0.0971109203},
{"learn":[2.690444602],"iteration":867,"passed_time":0.6336541466,"remaining_time":0.09636215132},
{"learn":[2.689044085],"iteration":868,"passed_time":0.6342754554,"remaining_time":0.0956157476},
{"learn":[2.686381682],"iteration":869,"passed_time":0.6349150303,"remaining_time":0.09487236085},
{"learn":[2.682406897],"iteration":870,"passed_time":0.6355228882,"remaining_time":0.09412451501},
{"learn":[2.679872023],"iteration":871,"passed_time":0.6362091366,"remaining_time":0.09338849712},
{"learn":[2.678955594],"iteration":872,"passed_time":0.6369612069,"remaining_time":0.0926621687},
{"learn":[2.677801225],"iteration":873,"passed_time":0.6384374897,"remaining_time":0.0920401873},
{"learn":[2.677286147],"iteration":874,"passed_time":0.6390888643,"remaining_time":0.09129840919},
{"learn":[2.675048154],"iteration":875,"passed_time":0.6397200468,"remaining_time":0.09055397922},
{"learn":[2.672657783],"iteration":876,"passed_time":0.6403236365,"remaining_time":0.08980593761},
{"learn":[2.671780422],"iteration":877,"passed_time":0.6409549074,"remaining_time":0.08906207141},
{"learn":[2.668990692],"iteration":878,"passed_time":0.6416539393,"remaining_time":0.08832778914},
{"learn":[2.668731553],"iteration":879,"passed_time":0.6424064657,"remaining_time":0.08760088168},
{"learn":[2.667805915],"iteration":880,"passed_time":0.6437462209,"remaining_time":0.08695323528},
{"learn":[2.666838897],"iteration":881,"passed_time":0.6448835998,"remaining_time":0.08627694419},
{"learn":[2.666309285],"iteration":882,"passed_time":0.6456512306,"remaining_time":0.08555061606},
{"learn":[2.663743163],"iteration":883,"passed_time":0.6464574026,"remaining_time":0.08482925193},
{"learn":[2.661767669],"iteration":884,"passed_time":0.6472238054,"remaining_time":0.08410252838},
{"learn":[2.660749737],"iteration":885,"passed_time":0.6479321973,"remaining_time":0.08336825113},
{"learn":[2.6586697],"iteration":886,"passed_time":0.648568672,"remaining_time":0.08262487027},
{"learn":[2.655929824],"iteration":887,"passed_time":0.6491821215,"remaining_time":0.08187882613},
{"learn":[2.654620233],"iteration":888,"passed_time":0.6498266423,"remaining_time":0.08113695984},
{"learn":[2.652822316],"iteration":889,"passed_time":0.6504837379,"remaining_time":0.08039686649},
{"learn":[2.650641409],"iteration":890,"passed_time":0.6511568885,"remaining_time":0.07965892351},
{"learn":[2.648781876],"iteration":891,"passed_time":0.6519274679,"remaining_time":0.07893292212},
{"learn":[2.64699437],"iteration":892,"passed_time":0.6526039802,"remaining_time":0.0781955497},
{"learn":[2.646161249],"iteration":893,"passed_time":0.6532209397,"remaining_time":0.07745125236},
{"learn":[2.645481819],"iteration":894,"passed_time":0.6538567878,"remaining_time":0.07670945555},
{"learn":[2.641620392],"iteration":895,"passed_time":0.6544723129,"remaining_time":0.07596553631},
{"learn":[2.639645343],"iteration":896,"passed_time":0.6550754882,"remaining_time":0.07522048527},
{"learn":[2.638033215],"iteration":897,"passed_time":0.6556800177,"remaining_time":0.07447590401},
{"learn":[2.636201637],"iteration":898,"passed_time":0.6562989776,"remaining_time":0.07373325555},
{"learn":[2.635376311],"iteration":899,"passed_time":0.656904796,"remaining_time":0.07298942178},
{"learn":[2.634885086],"iteration":900,"passed_time":0.6575164289,"remaining_time":0.07224653326},
{"learn":[2.633111035],"iteration":901,"passed_time":0.6583381289,"remaining_time":0.07152675902},
{"learn":[2.631371593],"iteration":902,"passed_time":0.6593294773,"remaining_time":0.07082498262},
{"learn":[2.629406406],"iteration":903,"passed_time":0.6600436559,"remaining_time":0.0700931316},
{"learn":[2.628883812],"iteration":904,"passed_time":0.6607660996,"remaining_time":0.06936218725},
{"learn":[2.626747953],"iteration":905,"passed_time":0.6614155772,"remaining_time":0.06862369123},
{"learn":[2.62552756],"iteration":906,"passed_time":0.662040975,"remaining_time":0.06788292247},
{"learn":[2.624256753],"iteration":907,"passed_time":0.6626717362,"remaining_time":0.06714295125},
{"learn":[2.622669203],"iteration":908,"passed_time":0.6632768646,"remaining_time":0.06640065421},
{"learn":[2.620248782],"iteration":909,"passed_time":0.6639071318,"remaining_time":0.06566114491},
{"learn":[2.618194295],"iteration":910,"passed_time":0.6645057526,"remaining_time":0.06491878373},
{"learn":[2.616186134],"iteration":911,"passed_time":0.6651713218,"remaining_time":0.06418319772},
{"learn":[2.613461679],"iteration":912,"passed_time":0.6657861721,"remaining_time":0.06344293206},
{"learn":[2.611929112],"iteration":913,"passed_time":0.6664323101,"remaining_time":0.06270588475},
{"learn":[2.608662079],"iteration":914,"passed_time":0.6671416318,"remaining_time":0.06197490569},
{"learn":[2.608006575],"iteration":915,"passed_time":0.6677800701,"remaining_time":0.06123747368},
{"learn":[2.606389222],"iteration":916,"passed_time":0.6683896673,"remaining_time":0.0604976471},
{"learn":[2.604740552],"iteration":917,"passed_time":0.6690112105,"remaining_time":0.05975917131},
{"learn":[2.601426336],"iteration":918,"passed_time":0.6696288287,"remaining_time":0.05902060405},
{"learn":[2.598375216],"iteration":919,"passed_time":0.6703186802,"remaining_time":0.05828858088},
{"learn":[2.598151475],"iteration":920,"passed_time":0.6710495673,"remaining_time":0.05756016918},
{"learn":[2.597823849],"iteration":921,"passed_time":0.6719592813,"remaining_time":0.05684688063},
{"learn":[2.594172502],"iteration":922,"passed_time":0.6727831617,"remaining_time":0.05612600591},
{"learn":[2.59375735],"iteration":923,"passed_time":0.6736888427,"remaining_time":0.05541163641},
{"learn":[2.591812328],"iteration":924,"passed_time":0.6744255872,"remaining_time":0.05468315572},
{"learn":[2.590122849],"iteration":925,"passed_time":0.6750318391,"remaining_time":0.05394422904},
{"learn":[2.589464237],"iteration":926,"passed_time":0.6756478956,"remaining_time":0.05320636071},
{"learn":[2.588424011],"iteration":927,"passed_time":0.6762761387,"remaining_time":0.05246970041},
{"learn":[2.585652028],"iteration":928,"passed_time":0.6768891899,"remaining_time":0.05173211247},
{"learn":[2.584041993],"iteration":929,"passed_time":0.6775034214,"remaining_time":0.05099488118},
{"learn":[2.583296049],"iteration":930,"passed_time":0.6781110718,"remaining_time":0.05025742637},
{"learn":[2.579914185],"iteration":931,"passed_time":0.6787261465,"remaining_time":0.0495207918},
{"learn":[2.576998572],"iteration":932,"passed_time":0.6793223816,"remaining_time":0.04878306491},
{"learn":[2.573910397],"iteration":933,"passed_time":0.6799161536,"remaining_time":0.04804546696},
{"learn":[2.571836709],"iteration":934,"passed_time":0.6805481303,"remaining_time":0.04731083259},
{"learn":[2.570234236],"iteration":935,"passed_time":0.6811670282,"remaining_time":0.04657552329},
{"learn":[2.568599038],"iteration":936,"passed_time":0.6817777137,"remaining_time":0.04583991031},
{"learn":[2.566914387],"iteration":937,"passed_time":0.682392793,"remaining_time":0.04510485412},
{"learn":[2.566021035],"iteration":938,"passed_time":0.683018645,"remaining_time":0.04437075329},
{"learn":[2.564809349],"iteration":939,"passed_time":0.6836446662,"remaining_time":0.04363689359},
{"learn":[2.564023959],"iteration":940,"passed_time":0.6842837509,"remaining_time":0.04290408215},
{"learn":[2.562986913],"iteration":941,"passed_time":0.6850675075,"remaining_time":0.04218037732},
{"learn":[2.558860237],"iteration":942,"passed_time":0.6858975386,"remaining_time":0.04145934221},
{"learn":[2.556025604],"iteration":943,"passed_time":0.6865484797,"remaining_time":0.04072745219},
{"learn":[2.554236499],"iteration":944,"passed_time":0.6871861636,"remaining_time":0.03999496191},
{"learn":[2.552492807],"iteration":945,"passed_time":0.6878309855,"remaining_time":0.03926307951},
{"learn":[2.551314144],"iteration":946,"passed_time":0.6884781355,"remaining_time":0.03853151128},
{"learn":[2.549586832],"iteration":947,"passed_time":0.6890718563,"remaining_time":0.03779719043},
{"learn":[2.548340934],"iteration":948,"passed_time":0.6896722638,"remaining_time":0.03706352524},
{"learn":[2.545835821],"iteration":949,"passed_time":0.6902632626,"remaining_time":0.0363296454},
{"learn":[2.542362157],"iteration":950,"passed_time":0.6908694969,"remaining_time":0.03559685105},
{"learn":[2.540961918],"iteration":951,"passed_time":0.6914767054,"remaining_time":0.0348643717},
{"learn":[2.538947245],"iteration":952,"passed_time":0.6920917617,"remaining_time":0.03413254229},
{"learn":[2.5382083],"iteration":953,"passed_time":0.6927360183,"remaining_time":0.03340236566},
{"learn":[2.535707641],"iteration":954,"passed_time":0.6934093312,"remaining_time":0.03267373812},
{"learn":[2.534405415],"iteration":955,"passed_time":0.694081892,"remaining_time":0.03194519168},
{"learn":[2.533752629],"iteration":956,"passed_time":0.6947471863,"remaining_time":0.03121643575},
{"learn":[2.530421298],"iteration":957,"passed_time":0.6953669404,"remaining_time":0.03048581576},
{"learn":[2.529240544],"iteration":958,"passed_time":0.6962530446,"remaining_time":0.02976681421},
{"learn":[2.526837207],"iteration":959,"passed_time":0.6969413219,"remaining_time":0.02903922174},
{"learn":[2.526134591],"iteration":960,"passed_time":0.6975924429,"remaining_time":0.0283102032},
{"learn":[2.525732951],"iteration":961,"passed_time":0.698234153,"remaining_time":0.02758097486},
{"learn":[2.523705935],"iteration":962,"passed_time":0.6988541017,"remaining_time":0.02685109217},
{"learn":[2.521172743],"iteration":963,"passed_time":0.6995527193,"remaining_time":0.02612437541},
{"learn":[2.52100878],"iteration":964,"passed_time":0.7003568733,"remaining_time":0.02540154463},
{"learn":[2.519425898],"iteration":965,"passed_time":0.7010062351,"remaining_time":0.0246730973},
{"learn":[2.517856048],"iteration":966,"passed_time":0.7016256232,"remaining_time":0.02394379066},
{"learn":[2.514501256],"iteration":967,"passed_time":0.7022354846,"remaining_time":0.02321439619},
{"learn":[2.512917005],"iteration":968,"passed_time":0.7028461924,"remaining_time":0.0224852755},
{"learn":[2.511558183],"iteration":969,"passed_time":0.7034452734,"remaining_time":0.02175603938},
{"learn":[2.511209657],"iteration":970,"passed_time":0.7040790836,"remaining_time":0.02102810857},
{"learn":[2.509740507],"iteration":971,"passed_time":0.7046675612,"remaining_time":0.02029906555},
{"learn":[2.50749253],"iteration":972,"passed_time":0.7053222121,"remaining_time":0.01957214772},
{"learn":[2.50573707],"iteration":973,"passed_time":0.7059104079,"remaining_time":0.01884360432},
{"learn":[2.504059642],"iteration":974,"passed_time":0.7064937703,"remaining_time":0.01811522488},
{"learn":[2.5028389],"iteration":975,"passed_time":0.707112175,"remaining_time":0.0173880043},
{"learn":[2.499774117],"iteration":976,"passed_time":0.7077323856,"remaining_time":0.016661049},
{"learn":[2.499376938],"iteration":977,"passed_time":0.7083520302,"remaining_time":0.01593429925},
{"learn":[2.497145667],"iteration":978,"passed_time":0.7090316225,"remaining_time":0.01520905421},
{"learn":[2.49556184],"iteration":979,"passed_time":0.7096739184,"remaining_time":0.01448314119},
{"learn":[2.493696094],"iteration":980,"passed_time":0.7103397216,"remaining_time":0.01375785394},
{"learn":[2.492885275],"iteration":981,"passed_time":0.7109893071,"remaining_time":0.01303239056},
{"learn":[2.489680099],"iteration":982,"passed_time":0.7116733031,"remaining_time":0.01230767666},
{"learn":[2.488890496],"iteration":983,"passed_time":0.7122641036,"remaining_time":0.01158153014},
{"learn":[2.485406665],"iteration":984,"passed_time":0.712859193,"remaining_time":0.01085572375},
{"learn":[2.483888201],"iteration":985,"passed_time":0.7134826639,"remaining_time":0.01013058549},
{"learn":[2.482963673],"iteration":986,"passed_time":0.7140864566,"remaining_time":0.009405394058},
{"learn":[2.480529095],"iteration":987,"passed_time":0.7146961453,"remaining_time":0.008680519983},
{"learn":[2.479266321],"iteration":988,"passed_time":0.7154177807,"remaining_time":0.007957123951},
{"learn":[2.478008968],"iteration":989,"passed_time":0.7160737229,"remaining_time":0.007233067908},
{"learn":[2.476620675],"iteration":990,"passed_time":0.7166824654,"remaining_time":0.006508720675},
{"learn":[2.474524348],"iteration":991,"passed_time":0.7173082722,"remaining_time":0.005784744131},
{"learn":[2.473486672],"iteration":992,"passed_time":0.7179436095,"remaining_time":0.005061032494},
{"learn":[2.472028928],"iteration":993,"passed_time":0.7185558475,"remaining_time":0.00433735924},
{"learn":[2.471248966],"iteration":994,"passed_time":0.7191484416,"remaining_time":0.003613811264},
{"learn":[2.468961169],"iteration":995,"passed_time":0.7197415098,"remaining_time":0.002890528152},
{"learn":[2.468487667],"iteration":996,"passed_time":0.720331281,"remaining_time":0.002167496332},
{"learn":[2.466340321],"iteration":997,"passed_time":0.7210100342,"remaining_time":0.001444909888},
{"learn":[2.464734555],"iteration":998,"passed_time":0.7216830699,"remaining_time":0.0007224054754},
{"learn":[2.463742874],"iteration":999,"passed_time":0.7228064296,"remaining_time":0}
]}